Workbook

Sheet Sovereign Wealth Funds
A1: Country | B1: Institution | C1: Mandate type | D1: Established | E1: AUM (USD m, approx) | F1: As-of year | G1: Currency basis (local) | H1: Owner / Regulator | I1: Public reporting | J1: Confidence | K1: Notes
A2: Algeria | B2: Fonds de Régulation des Recettes (FRR) | C2: Stabilisation | D2: 2000 | F2: n/a | G2: DZD | H2: Ministry of Finance | I2: Limited | J2: L | K2: Oil revenue stabilisation fund; depleted during 2014–17 oil price crash; balance not regularly disclosed.
A3: Angola | B3: Fundo Soberano de Angola (FSDEA) | C3: Savings / Strategic | D3: 2012 | E3: 3400 | F3: 2023 | G3: USD | H3: Ministry of Finance | I3: Yes (annual report) | J3: H | K3: Has disclosed PE/infra allocations including African private equity exposure.
A4: Botswana | B4: Pula Fund | C4: Savings | D4: 1994 | E4: 5000 | F4: 2024 | G4: USD/BWP | H4: Bank of Botswana | I4: Yes (BoB annual report) | J4: H | K4: Managed within Bank of Botswana FX reserves; primarily global fixed income & equities, limited alts.
A5: Djibouti | B5: Fonds Souverain de Djibouti (FSD) | C5: Strategic / Development | D5: 2020 | E5: 1500 | F5: 2024 | G5: USD | H5: Government of Djibouti | I5: Limited | J5: M | K5: Newer SWF; mandate includes domestic strategic investments.
A6: Egypt | B6: The Sovereign Fund of Egypt (TSFE) | C6: Strategic / Development | D6: 2018 | E6: 2500 | F6: 2024 | G6: USD | H6: Government of Egypt | I6: Yes (annual report) | J6: H | K6: Active in SOE divestiture and co-investments; signed partnerships with ADQ, PIF, BlackRock.
A7: Equatorial Guinea | B7: Fund for Future Generations (FFG) | C7: Savings | D7: 2002 | E7: 80 | F7: approx | G7: USD/XAF | H7: Ministry of Finance | I7: Very limited | J7: L | K7: Small, opaque oil-revenue savings vehicle.
A8: Ethiopia | B8: Ethiopian Investment Holdings (EIH) | C8: Strategic (SOE holding) | D8: 2022 | E8: 38000 | F8: 2024 | G8: ETB | H8: Office of the Prime Minister | I8: Limited | J8: M | K8: Holds equity in major SOEs (Ethio Telecom, EthAir, CBE); AUM is book value of SOE stakes, not liquid investable capital.
A9: Gabon | B9: Fonds Gabonais d'Investissements Stratégiques (FGIS) | C9: Strategic / Savings | D9: 2012 | E9: 1500 | F9: 2023 | G9: USD/XAF | H9: Government of Gabon | I9: Limited | J9: M | K9: Has stakes in Gabonese financial sector and Africa-focused infrastructure platforms.
A10: Ghana | B10: Ghana Stabilisation Fund (GSF) | C10: Stabilisation | D10: 2011 | E10: 750 | F10: 2024 | G10: USD | H10: Ministry of Finance / BoG | I10: Yes (Petroleum Funds Report) | J10: H | K10: By law invested in high-grade fixed income; not in scope for alts.
A11: Ghana | B11: Ghana Heritage Fund (GHF) | C11: Savings (intergenerational) | D11: 2011 | E11: 1100 | F11: 2024 | G11: USD | H11: Ministry of Finance / BoG | I11: Yes (Petroleum Funds Report) | J11: H | K11: By law invested in qualifying instruments; alts effectively prohibited.
A12: Ghana | B12: Ghana Infrastructure Investment Fund (GIIF) | C12: Strategic / Infrastructure | D12: 2014 | E12: 400 | F12: 2023 | G12: USD | H12: Government of Ghana | I12: Limited | J12: M | K12: Mandate is infrastructure investment in Ghana; in scope for direct deals.
A13: Libya | B13: Libyan Investment Authority (LIA) | C13: Savings / Strategic | D13: 2006 | E13: 67000 | F13: 2023 | G13: USD | H13: Government of Libya | I13: Limited (assets largely frozen) | J13: M | K13: Bulk of assets frozen under UN sanctions since 2011; governance contested.
A14: Mauritania | B14: Fonds National des Revenus des Hydrocarbures (FNRH) | C14: Stabilisation / Savings | D14: 2006 | E14: 200 | F14: approx | G14: USD/MRU | H14: BCM / Ministry of Finance | I14: Limited | J14: L | K14: Small hydrocarbons revenue fund.
A15: Morocco | B15: Ithmar Capital | C15: Strategic / Development | D15: 2011 | E15: 1000 | F15: 2023 | G15: USD | H15: Government of Morocco | I15: Yes | J15: H | K15: Tourism, hospitality, renewable infra mandate; co-investor with Green Africa Investment, AfDB.
A16: Morocco | B16: Mohammed VI Fund for Investment | C16: Strategic | D16: 2020 | E16: 4500 | F16: 2024 | G16: USD/MAD | H16: Government of Morocco | I16: Limited | J16: M | K16: Capitalised at MAD 45bn (≈USD 4.5bn); mandates include backing of sectoral funds.
A17: Namibia | B17: Welwitschia Sovereign Wealth Fund | C17: Savings | D17: 2022 | E17: 60 | F17: 2024 | G17: USD | H17: Bank of Namibia | I17: Limited | J17: L | K17: Newly established; very small.
A18: Nigeria | B18: Nigeria Sovereign Investment Authority (NSIA) | C18: Savings + Stabilisation + Infrastructure (3 sub-funds) | D18: 2011 | E18: 2900 | F18: 2023 | G18: USD | H18: Federal Ministry of Finance | I18: Yes (annual report) | J18: H | K18: Most operationally relevant of the three sub-funds is the Nigeria Infrastructure Fund (NIF) — active co-investor.
A19: Rwanda | B19: Agaciro Development Fund (AgDF) | C19: Savings / Strategic | D19: 2012 | E19: 220 | F19: 2023 | G19: USD/RWF | H19: Government of Rwanda | I19: Limited | J19: M | K19: Smaller fund but has made domestic strategic investments.
A20: São Tomé and Príncipe | B20: National Oil Account | C20: Stabilisation / Savings | D20: 2004 | E20: 20 | F20: approx | G20: USD | H20: Central Bank of STP | I20: Limited | J20: L | K20: Small; oil revenues.
A21: Senegal | B21: Fonds Souverain d'Investissements Stratégiques (FONSIS) | C21: Strategic / Development | D21: 2012 | E21: 1000 | F21: 2023 | G21: USD/XOF | H21: Government of Senegal | I21: Yes (annual report) | J21: H | K21: Active strategic investor; portfolio includes hotels, agribusiness, infra; co-invests with DFIs.
A22: Zimbabwe | B22: Sovereign Wealth Fund of Zimbabwe (SWFZ) | C22: Savings / Strategic | D22: 2014 | E22: 0 | F22: n/a | G22: USD | H22: Government of Zimbabwe | I22: Limited | J22: L | K22: Established by law but minimally capitalised; effectively dormant.
A23: Kenya | B23: Kenya Sovereign Wealth Fund (proposed) | C23: Planned | D23: TBD | E23: 0 | F23: n/a | G23: n/a | H23: Treasury / CBK | I23: n/a | J23: L | K23: Discussed for over a decade; no operating fund. Exclude from active universe.
A24: Tanzania | B24: Tanzania SWF (proposed for gas revenues) | C24: Planned | D24: TBD | E24: 0 | F24: n/a | G24: n/a | H24: Ministry of Finance | I24: n/a | J24: L | K24: Not yet operational.
A25: Uganda | B25: Petroleum Revenue Investment Reserve (PRIR) | C25: Stabilisation / Savings | D25: 2015 | E25: 100 | F25: 2024 | G25: USD/UGX | H25: Bank of Uganda | I25: Yes (BoU) | J25: M | K25: Petroleum Fund under PFMA 2015; small balance pending major oil production.
A26: Cabo Verde | B26: — | C26: n/a | D26: n/a | E26: 0 | F26: n/a | G26: n/a | H26: n/a | I26: n/a | J26: n/a | K26: No SWF.
A27: Chad | B27: Fonds de Stabilisation des Recettes Pétrolières (defunct) | C27: Stabilisation | D27: 1999 | E27: 0 | F27: n/a | G27: n/a | H27: Ministry of Finance | I27: n/a | J27: L | K27: Effectively wound down.

Sheet Pension Funds
A1: Country | B1: Institution | C1: Type | D1: Established | E1: AUM (USD m, approx) | F1: As-of year | G1: Currency basis (local) | H1: Regulator | I1: Public reporting | J1: Confidence | K1: Notes
A2: South Africa | B2: Government Employees Pension Fund (GEPF) | C2: Defined benefit, public sector | D2: 1996 | E2: 125000 | F2: 2024 | G2: ZAR | H2: FSCA + PIC (manager) | I2: Yes (annual report) | J2: H | K2: Largest pension fund in Africa; managed by PIC. Reg 28 allows up to 15% in private markets including ~10% in Africa-ex-SA assets.
A3: South Africa | B3: Eskom Pension and Provident Fund (EPPF) | C3: Hybrid, parastatal | D3: 1973 | E3: 10000 | F3: 2024 | G3: ZAR | H3: FSCA | I3: Yes | J3: H | K3: Active in SA and Africa alternatives via mandate managers.
A4: South Africa | B4: Transnet Retirement Fund | C4: DC, parastatal | D4: 2000 | E4: 5500 | F4: 2024 | G4: ZAR | H4: FSCA | I4: Yes | J4: H | K4: Also: Transnet Second Defined Benefit Fund.
A5: South Africa | B5: Sentinel Retirement Fund | C5: DC, multi-employer (mining) | D5: 1946 | E5: 6000 | F5: 2024 | G5: ZAR | H5: FSCA | I5: Yes | J5: H | K5: Mining industry; uses external alts mandates.
A6: South Africa | B6: Sasol Pension Fund | C6: Hybrid, corporate | D6: 1953 | E6: 2000 | F6: 2023 | G6: ZAR | H6: FSCA | I6: Yes | J6: M | K6: Corporate scheme.
A7: South Africa | B7: Telkom Retirement Fund | C7: DC, parastatal | D7: 1992 | E7: 2500 | F7: 2023 | G7: ZAR | H7: FSCA | I7: Yes | J7: M | K7: Parastatal scheme.
A8: South Africa | B8: AECI Pension Fund | C8: Corporate | D8: 1923 | E8: 1500 | F8: 2023 | G8: ZAR | H8: FSCA | I8: Yes | J8: M | K8: Long-running industrial pension.
A9: South Africa | B9: Municipal Employees' Pension Fund (MEPF) | C9: Public sector | D9: 1986 | E9: 2000 | F9: 2023 | G9: ZAR | H9: FSCA | I9: Yes | J9: M | K9: Local government employees.
A10: South Africa | B10: Municipal Workers Retirement Fund (MWRF) | C10: Public sector | D10: 1996 | E10: 1500 | F10: 2023 | G10: ZAR | H10: FSCA | I10: Yes | J10: M | K10: Local government employees.
A11: South Africa | B11: Mineworkers Provident Fund (MWPF) | C11: Multi-employer (mining) | D11: 1989 | E11: 1200 | F11: 2023 | G11: ZAR | H11: FSCA | I11: Yes | J11: M | K11: Industry scheme.
A12: South Africa | B12: Old Mutual Super Fund (umbrella) | C12: Umbrella DC | D12: 2003 | E12: 8000 | F12: 2024 | G12: ZAR | H12: FSCA | I12: Yes | J12: M | K12: Umbrella fund — large indirect asset owner.
A13: South Africa | B13: Sanlam Umbrella Fund | C13: Umbrella DC | D13: 2007 | E13: 10000 | F13: 2024 | G13: ZAR | H13: FSCA | I13: Yes | J13: M | K13: Umbrella fund.
... A15: Nigeria | B15: Stanbic IBTC Pension Managers | C15: PFA | D15: 2004 | E15: 3500 | F15: 2024 | G15: NGN | H15: PenCom | I15: Yes (PenCom returns) | J15: H | K15: Largest PFA by AUM.
A16: Nigeria | B16: ARM Pension Managers | C16: PFA | D16: 2005 | E16: 1800 | F16: 2024 | G16: NGN | H16: PenCom | I16: Yes | J16: H
A17: Nigeria | B17: Premium Pension Limited | C17: PFA | D17: 2005 | E17: 1500 | F17: 2024 | G17: NGN | H17: PenCom | I17: Yes | J17: H
A18: Nigeria | B18: Tangerine APT Pensions (post-merger) | C18: PFA | D18: 2005 | E18: 1200 | F18: 2024 | G18: NGN | H18: PenCom | I18: Yes | J18: H | K18: Formed from Tangerine + APT merger.
A19: Nigeria | B19: Trustfund Pensions | C19: PFA | D19: 2005 | E19: 900 | F19: 2024 | G19: NGN | H19: PenCom | I19: Yes | J19: H
A20: Nigeria | B20: Sigma Pensions (Access Pensions post-merger) | C20: PFA | D20: 2005 | E20: 1100 | F20: 2024 | G20: NGN | H20: PenCom | I20: Yes | J20: H | K20: Acquired by Access Holdings.
A21: Nigeria | B21: Leadway Pensure PFA | C21: PFA | D21: 2005 | E21: 700 | F21: 2024 | G21: NGN | H21: PenCom | I21: Yes | J21: M
A22: Nigeria | B22: NPF Pensions | C22: PFA | D22: 2012 | E22: 500 | F22: 2024 | G22: NGN | H22: PenCom | I22: Yes | J22: M | K22: Police pension; closed scheme model.
A23: Nigeria | B23: Crusader Sterling Pensions | C23: PFA | D23: 2005 | E23: 600 | F23: 2024 | G23: NGN | H23: PenCom | I23: Yes | J23: M
A24: Nigeria | B24: Pensions Alliance (PAL Pensions) | C24: PFA | D24: 2005 | E24: 600 | F24: 2024 | G24: NGN | H24: PenCom | I24: Yes | J24: M
A25: Nigeria | B25: AIICO Pension Managers | C25: PFA | D25: 2005 | E25: 400 | F25: 2024 | G25: NGN | H25: PenCom | I25: Yes | J25: M
A26: Nigeria | B26: FCMB Pensions | C26: PFA | D26: 2005 | E26: 500 | F26: 2024 | G26: NGN | H26: PenCom | I26: Yes | J26: M
A27: Nigeria | B27: Fidelity Pension Managers | C27: PFA | D27: 2005 | E27: 400 | F27: 2024 | G27: NGN | H27: PenCom | I27: Yes | J27: M
A28: Nigeria | B28: NLPC Pension Fund Administrators | C28: PFA | D28: 2005 | E28: 350 | F28: 2024 | G28: NGN | H28: PenCom | I28: Yes | J28: M
A29: Nigeria | B29: Veritas Glanvill Pensions | C29: PFA | D29: 2005 | E29: 300 | F29: 2024 | G29: NGN | H29: PenCom | I29: Yes | J29: M
A30: Nigeria | B30: IEI-Anchor Pension Managers | C30: PFA | D30: 2007 | E30: 250 | F30: 2024 | G30: NGN | H30: PenCom | I30: Yes | J30: M
A31: Nigeria | B31: Norrenberger Pensions | C31: PFA | D31: 2005 | E31: 200 | F31: 2024 | G31: NGN | H31: PenCom | I31: Yes | J31: L
A32: Nigeria | B32: Radix Pension Managers | C32: PFA | D32: 2005 | E32: 150 | F32: 2024 | G32: NGN | H32: PenCom | I32: Yes | J32: L
A33: Nigeria | B33: Nigeria Social Insurance Trust Fund (NSITF) | C33: Public, employee compensation | D33: 1993 | E33: 350 | F33: 2023 | G33: NGN | H33: Federal MoL | I33: Limited | J33: L | K33: Separate from CPS PFA universe.
A34: Kenya | B34: National Social Security Fund (NSSF Kenya) | C34: Public, mandatory | D34: 1965 | E34: 3200 | F34: 2024 | G34: KES | H34: RBA | I34: Yes | J34: H | K34: Largest single Kenyan pension fund.
A35: Kenya | B35: Kenya Power Pension Fund (KPPF) | C35: Occupational, parastatal | D35: 1955 | E35: 800 | F35: 2024 | G35: KES | H35: RBA | I35: Yes | J35: H
A36: Kenya | B36: Local Authorities Pension Trust (LAPTRUST) | C36: Occupational, local gov't | D36: 1929 | E36: 700 | F36: 2024 | G36: KES | H36: RBA | I36: Yes | J36: H
A37: Kenya | B37: County Pension Fund (CPF Financial Services) | C37: Umbrella | D37: 1929 | E37: 800 | F37: 2024 | G37: KES | H37: RBA | I37: Yes | J37: M
A38: Kenya | B38: Telposta Pension Scheme | C38: Occupational, parastatal | D38: 1999 | E38: 350 | F38: 2023 | G38: KES | H38: RBA | I38: Yes | J38: M
A39: Kenya | B39: KPLC Staff Retirement Benefits Scheme | C39: Occupational | D39: 2006 | E39: 300 | F39: 2023 | G39: KES | H39: RBA | I39: Yes | J39: M
A40: Kenya | B40: Public Service Superannuation Scheme (PSSS) | C40: Public, civil service | D40: 2012 | E40: 200 | F40: 2024 | G40: KES | H40: RBA | I40: Limited | J40: M | K40: Newer DC scheme for new civil servants.
A41: Ghana | B41: Social Security and National Insurance Trust (SSNIT) | C41: Public, mandatory | D41: 1972 | E41: 3000 | F41: 2023 | G41: GHS | H41: NPRA | I41: Yes (annual report) | J41: H | K41: Largest pension fund in West Africa ex-Nigeria.
A42: Ghana | B42: Tier 2 Corporate Trustees (umbrella schemes) | C42: DC, mandatory | D42: various | E42: 3500 | F42: 2023 | G42: GHS | H42: NPRA | I42: Aggregate via NPRA | J42: M | K42: Universe of Tier 2 trustees; aggregate not allocator-level.
A43: Uganda | B43: National Social Security Fund (NSSF Uganda) | C43: Public, mandatory | D43: 1985 | E43: 5800 | F43: 2024 | G43: UGX | H43: URBRA | I43: Yes (annual report) | J43: H | K43: Highly active allocator; has made disclosed Africa alts commitments.
A44: Tanzania | B44: Public Service Social Security Fund (PSSSF) | C44: Public, civil service consolidated | D44: 2018 | E44: 6000 | F44: 2024 | G44: TZS | H44: SSRA | I44: Yes | J44: H | K44: Merger of PSPF, GEPF, LAPF, PPF.
A45: Tanzania | B45: National Social Security Fund (NSSF Tanzania) | C45: Public, private sector | D45: 1997 | E45: 1700 | F45: 2024 | G45: TZS | H45: SSRA | I45: Yes | J45: H
A46: Tanzania | B46: Workers Compensation Fund (WCF) | C46: Public, workers comp | D46: 2015 | E46: 250 | F46: 2023 | G46: TZS | H46: SSRA | I46: Yes | J46: M
A47: Rwanda | B47: Rwanda Social Security Board (RSSB) | C47: Public, mandatory | D47: 2010 | E47: 1500 | F47: 2024 | G47: RWF | H47: MINECOFIN | I47: Yes | J47: H | K47: Manages pension + medical + occupational hazards branches.
A48: Zambia | B48: National Pension Scheme Authority (NAPSA) | C48: Public, mandatory | D48: 1996 | E48: 2600 | F48: 2024 | G48: ZMW | H48: PIA | I48: Yes | J48: H
A49: Zambia | B49: Local Authorities Superannuation Fund (LASF) | C49: Occupational, local gov't | D49: 1958 | E49: 200 | F49: 2023 | G49: ZMW | H49: PIA | I49: Limited | J49: M
A50: Zambia | B50: Public Service Pension Fund (PSPF) | C50: Public, civil service | D50: 1996 | E50: 350 | F50: 2023 | G50: ZMW | H50: PIA | I50: Limited | J50: M
A51: Zimbabwe | B51: National Social Security Authority (NSSA) | C51: Public, mandatory | D51: 1989 | E51: 500 | F51: 2023 | G51: USD/ZWL | H51: IPEC | I51: Yes (limited) | J51: M | K51: Hyperinflation has distorted historical AUM.
A52: Zimbabwe | B52: Mining Industry Pension Fund (MIPF) | C52: Multi-employer | D52: 1982 | E52: 400 | F52: 2023 | G52: USD | H52: IPEC | I52: Yes | J52: M
A53: Zimbabwe | B53: Local Authorities Pension Fund (LAPF) | C53: Occupational, local gov't | D53: 1948 | E53: 300 | F53: 2023 | G53: USD | H53: IPEC | I53: Yes | J53: M
A54: Mozambique | B54: Instituto Nacional de Segurança Social (INSS) | C54: Public, mandatory | D54: 1989 | E54: 800 | F54: 2023 | G54: MZN | H54: Ministry of Labour | I54: Limited | J54: L
A55: Angola | B55: Instituto Nacional de Segurança Social (INSS Angola) | C55: Public, mandatory | D55: 1991 | E55: 900 | F55: 2023 | G55: AOA | H55: Ministry of Public Admin | I55: Limited | J55: L
A56: Botswana | B56: Botswana Public Officers Pension Fund (BPOPF) | C56: Public sector | D56: 2001 | E56: 7500 | F56: 2024 | G56: BWP | H56: NBFIRA | I56: Yes (annual report) | J56: H | K56: Largest pension fund in Botswana; active in alts.
A57: Botswana | B57: Debswana Pension Fund | C57: Corporate (mining JV) | D57: 1984 | E57: 1500 | F57: 2024 | G57: BWP | H57: NBFIRA | I57: Yes | J57: H | K57: De Beers / Government JV mining co. fund; alts-active.
A58: Botswana | B58: Motor Vehicle Accident Fund (MVA) | C58: Statutory | D58: 1987 | E58: 400 | F58: 2023 | G58: BWP | H58: NBFIRA | I58: Yes | J58: M
A59: Namibia | B59: Government Institutions Pension Fund (GIPF) | C59: Public sector | D59: 1989 | E59: 9500 | F59: 2024 | G59: NAD | H59: NAMFISA | I59: Yes (annual report) | J59: H | K59: One of the most alts-active African pension funds; mandates an explicit unlisted-investment programme via SME/PE managers.
A60: Namibia | B60: Old Mutual Namibia retirement funds | C60: DC umbrella | D60: 1920 | E60: 2000 | F60: 2024 | G60: NAD | H60: NAMFISA | I60: Yes | J60: M
A61: Namibia | B61: NAMCOR / parastatal pension schemes | C61: Various | D61: various | E61: 500 | F61: 2023 | G61: NAD | H61: NAMFISA | I61: Limited | J61: L
A62: Mauritius | B62: National Pensions Fund (NPF) | C62: Public, contributory | D62: 1976 | E62: 3000 | F62: 2024 | G62: MUR | H62: FSC / Min. Social Security | I62: Yes | J62: H | K62: Replaced by Contribution Sociale Généralisée (CSG) for new flows from 2020; NPF runs off legacy.
A63: Mauritius | B63: SICOM Pension Schemes (parastatal) | C63: Multi-employer parastatal | D63: 1995 | E63: 1200 | F63: 2024 | G63: MUR | H63: FSC | I63: Yes | J63: M
A64: Mauritius | B64: Civil Service Family Protection Scheme (CSFPS) | C64: Public sector | D64: 1968 | E64: 600 | F64: 2023 | G64: MUR | H64: FSC | I64: Yes | J64: M
A65: Eswatini | B65: Public Service Pensions Fund (PSPF Eswatini) | C65: Public sector | D65: 1993 | E65: 800 | F65: 2023 | G65: SZL | H65: FSRA | I65: Yes | J65: M | K65: Defined benefit civil-service scheme.
A66: Eswatini | B66: Eswatini National Provident Fund (ENPF) | C66: Public, mandatory | D66: 1974 | E66: 350 | F66: 2023 | G66: SZL | H66: FSRA | I66: Yes | J66: M
A67: Lesotho | B67: Public Officers' Defined Contribution Pension Fund (PODCPF) | C67: Public sector | D67: 2008 | E67: 400 | F67: 2023 | G67: LSL | H67: CBL | I67: Yes | J67: M
A68: Madagascar | B68: Caisse Nationale de Prévoyance Sociale (CNaPS) | C68: Public, mandatory | D68: 1969 | E68: 250 | F68: 2023 | G68: MGA | H68: Min. Social Affairs | I68: Limited | J68: L
A69: Madagascar | B69: Caisse de Retraite et de Prévoyance Sociale (CRCM, civil servants) | C69: Public sector | D69: various | E69: 300 | F69: 2023 | G69: MGA | H69: Min. Finance | I69: Limited | J69: L
A70: Malawi | B70: NICO Pension Services (largest private trustee) | C70: Private trustee | D70: 2011 | E70: 600 | F70: 2023 | G70: MWK | H70: RBM | I70: Yes | J70: M | K70: Pension reform 2011 created funded system.
A71: Malawi | B71: Old Mutual Pension Services Malawi | C71: Private trustee | D71: 2011 | E71: 500 | F71: 2023 | G71: MWK | H71: RBM | I71: Yes | J71: M
A72: Senegal | B72: Institut de Prévoyance Retraite du Sénégal (IPRES) | C72: Private sector | D72: 1958 | E72: 800 | F72: 2023 | G72: XOF | H72: CIPRES | I72: Yes | J72: M
A73: Senegal | B73: Fonds National de Retraite (FNR) | C73: Civil service | D73: 1981 | E73: 400 | F73: 2023 | G73: XOF | H73: Min. Finance | I73: Limited | J73: M
A74: Senegal | B74: Caisse de Sécurité Sociale (CSS) | C74: Family allowances + workers comp | D74: 1973 | E74: 200 | F74: 2023 | G74: XOF | H74: CIPRES | I74: Limited | J74: L
A75: Côte d'Ivoire | B75: Caisse Générale de Retraite des Agents de l'État (CGRAE) | C75: Civil service | D75: 1958 | E75: 1800 | F75: 2024 | G75: XOF | H75: Min. Finance / CIPRES | I75: Yes | J75: M
A76: Côte d'Ivoire | B76: Caisse Nationale de Prévoyance Sociale (CNPS-CI) | C76: Private sector | D76: 1968 | E76: 1500 | F76: 2024 | G76: XOF | H76: CIPRES | I76: Yes | J76: M
A77: Cameroon | B77: Caisse Nationale de Prévoyance Sociale (CNPS Cameroon) | C77: Mandatory | D77: 1969 | E77: 900 | F77: 2023 | G77: XAF | H77: CIPRES | I77: Limited | J77: M
A78: Gabon | B78: Caisse Nationale de Sécurité Sociale (CNSS Gabon) | C78: Private sector | D78: 1963 | E78: 500 | F78: 2023 | G78: XAF | H78: CIPRES | I78: Limited | J78: M
A79: Gabon | B79: Caisse de Pensions et de Prestations Familiales des Agents de l'État (CPPF) | C79: Civil service | D79: 1983 | E79: 400 | F79: 2023 | G79: XAF | H79: Min. Finance | I79: Limited | J79: L
A80: DR Congo | B80: Caisse Nationale de Sécurité Sociale (CNSS DRC) | C80: Private sector | D80: 1961 | E80: 400 | F80: 2023 | G80: USD | H80: Min. Social Affairs | I80: Limited | J80: L
A81: DR Congo | B81: Institut National de Préparation Professionnelle (INPP) / civil service | C81: Civil service | D81: various | E81: 200 | F81: 2023 | G81: USD | H81: Min. Finance | I81: Limited | J81: L
A82: Ethiopia | B82: Public Servants Social Security Agency (POESSA) | C82: Civil service | D82: 2010 | E82: 3500 | F82: 2024 | G82: ETB | H82: MoF | I82: Yes (limited) | J82: M | K82: Largest public-pension AUM in Horn of Africa; primarily invested in government securities.
A83: Ethiopia | B83: Private Organizations Employees Social Security Agency (POSSA) | C83: Private sector | D83: 2011 | E83: 1500 | F83: 2024 | G83: ETB | H83: MoF | I83: Yes (limited) | J83: M
A84: Egypt | B84: National Social Insurance Authority (NOSI / NSSA) | C84: Public, mandatory (consolidated) | D84: 2019 | E84: 110000 | F84: 2024 | G84: EGP | H84: FRA | I84: Yes | J84: M | K84: Successor to merged civil-service + general pension authorities; vast AUM mostly in EGP gov't paper. Africa-alts exposure historically minimal.
A85: Egypt | B85: National Investment Bank (NIB) - legacy pension assets | C85: Sovereign deposit / pension reserves | D85: 1980 | E85: 30000 | F85: 2023 | G85: EGP | H85: MoF / CBE | I85: Limited | J85: L | K85: Has historically held pension surpluses; structure under reform.
A86: Morocco | B86: Caisse de Dépôt et de Gestion (CDG) | C86: Sovereign financial group + pension manager | D86: 1959 | E86: 28000 | F86: 2024 | G86: MAD | H86: Min. Finance | I86: Yes (annual report) | J86: H | K86: Holds and manages pension reserves; major LP in Moroccan and pan-African PE/infrastructure.
A87: Morocco | B87: Caisse Marocaine des Retraites (CMR) | C87: Civil service | D87: 1930 | E87: 14500 | F87: 2024 | G87: MAD | H87: ACAPS | I87: Yes | J87: H
A88: Morocco | B88: Caisse Nationale de Sécurité Sociale (CNSS Morocco) | C88: Private sector | D88: 1959 | E88: 8500 | F88: 2024 | G88: MAD | H88: ACAPS | I88: Yes | J88: H
A89: Morocco | B89: Régime Collectif d'Allocation de Retraite (RCAR) | C89: Parastatal | D89: 1977 | E89: 13000 | F89: 2024 | G89: MAD | H89: ACAPS | I89: Yes | J89: H | K89: Managed by CDG.
A90: Morocco | B90: Caisse Interprofessionnelle Marocaine de Retraite (CIMR) | C90: Private complementary | D90: 1949 | E90: 8500 | F90: 2024 | G90: MAD | H90: ACAPS | I90: Yes | J90: H | K90: Voluntary supplementary scheme.
A91: Tunisia | B91: Caisse Nationale de Sécurité Sociale (CNSS Tunisia) | C91: Private sector | D91: 1960 | E91: 1500 | F91: 2023 | G91: TND | H91: Min. Social Affairs | I91: Yes | J91: M
A92: Tunisia | B92: Caisse Nationale de Retraite et de Prévoyance Sociale (CNRPS) | C92: Civil service | D92: 1975 | E92: 2200 | F92: 2023 | G92: TND | H92: Min. Social Affairs | I92: Yes | J92: M
A93: Tunisia | B93: Caisse d'Assurance Maladie (CNAM) | C93: Health insurance | D93: 2004 | E93: 600 | F93: 2023 | G93: TND | H93: Min. Social Affairs | I93: Limited | J93: L
A94: Algeria | B94: Caisse Nationale des Retraites (CNR) | C94: Public, mandatory | D94: 1983 | E94: 3000 | F94: 2023 | G94: DZD | H94: Min. Labour / Social Security | I94: Limited | J94: M
A95: Algeria | B95: Caisse Nationale des Assurances Sociales (CNAS) | C95: Salaried workers | D95: 1992 | E95: 1500 | F95: 2023 | G95: DZD | H95: Min. Labour | I95: Limited | J95: M
A96: Algeria | B96: Caisse Nationale de Sécurité Sociale des Non-Salariés (CASNOS) | C96: Self-employed | D96: 1992 | E96: 400 | F96: 2023 | G96: DZD | H96: Min. Labour | I96: Limited | J96: L
A97: Libya | B97: Social Security Fund of Libya (SSF) | C97: Public, mandatory | D97: 1980 | E97: 9000 | F97: 2023 | G97: LYD | H97: Min. Social Affairs | I97: Limited | J97: L | K97: Largely invested in domestic deposits; political instability constrains AM.
A98: Burkina Faso | B98: Caisse Nationale de Sécurité Sociale (CNSS Burkina) | C98: Mandatory | D98: 1955 | E98: 600 | F98: 2023 | G98: XOF | H98: CIPRES | I98: Limited | J98: M
A99: Burkina Faso | B99: Caisse Autonome de Retraite des Fonctionnaires (CARFO) | C99: Civil service | D99: 1986 | E99: 400 | F99: 2023 | G99: XOF | H99: Min. Finance | I99: Limited | J99: M
A100: Mali | B100: Institut National de Prévoyance Sociale (INPS Mali) | C100: Mandatory | D100: 1961 | E100: 300 | F100: 2023 | G100: XOF | H100: CIPRES | I100: Limited | J100: L
A101: Mali | B101: Caisse Malienne de Sécurité Sociale (CMSS) | C101: Civil service | D101: 1961 | E101: 250 | F101: 2023 | G101: XOF | H101: Min. Finance | I101: Limited | J101: L
...

Sheet Tier 1 Candidates
A1: Tier 1 deep-dive candidates — institutions with AUM ≥ USD 2bn where alts-evidence collection should be exhaustive. These represent the bulk of African institutional capital that could realistically deploy to alts.
A3: Country | B3: Institution | C3: Type | D3: AUM (USD m, approx) | E3: As-of year | F3: Why prioritised | G3: Known/expected African alts evidence
A4: South Africa | B4: GEPF (managed by PIC) | C4: Public PF (DB) | D4: 125000 | E4: 2024 | F4: By far the largest African pension pool | G4: Disclosed PE/infra exposure including Africa-ex-SA via PIC's Isibaya programme; LP in DPI, Helios, others (historical).
A5: Egypt | B5: NOSI / NSSA | C5: Public PF (consolidated) | D5: 110000 | E5: 2024 | F5: Largest in North Africa by AUM | G5: Predominantly EGP government securities; Africa alts exposure historically minimal but worth verifying post-2019 reforms.
A6: Libya | B6: Libyan Investment Authority | C6: SWF | D6: 67000 | E6: 2023 | F6: Largest African SWF by stated AUM | G6: Mostly frozen since 2011; Pre-2011 had direct African stakes (banking, telecoms) — investigate legacy holdings.
A7: Ethiopia | B7: Ethiopian Investment Holdings (EIH) | C7: Strategic SWF (SOE holding) | D7: 38000 | E7: 2024 | F7: Largest SoE consolidator | G7: AUM is book value of SOE stakes; not a traditional LP. Verify any third-party fund commitments.
A8: Egypt | B8: NIB legacy pension assets | C8: Sovereign deposit | D8: 30000 | E8: 2023 | F8: Historic pension surplus pool | G8: Structure under reform; verify current asset mix.
A9: Morocco | B9: Caisse de Dépôt et de Gestion (CDG) | C9: Sovereign + pension manager | D9: 28000 | E9: 2024 | F9: Largest French-speaking Africa allocator | G9: Confirmed LP in pan-African and Moroccan PE/infra (CDG Capital, Mediterrania Capital, AfricInvest funds).
A10: Morocco | B10: CMR | C10: Civil-service PF | D10: 14500 | E10: 2024 | F10: Large Moroccan pension allocator | G10: Verify alts mandate; recent reform allowing higher alts limit.
A11: Morocco | B11: RCAR (CDG-managed) | C11: Parastatal PF | D11: 13000 | E11: 2024 | F11: Large allocator under CDG | G11: Alts exposure via CDG Capital infrastructure and PE funds.
A12: Egypt | B12: The Sovereign Fund of Egypt (TSFE) | C12: SWF (strategic) | D12: 2500 | E12: 2024 | F12: Active strategic investor | G12: Joint platforms with ADQ, PIF; co-investments in renewables, healthcare, fintech.
A13: Namibia | B13: GIPF | C13: Public PF (DB) | D13: 9500 | E13: 2024 | F13: Among most alts-active African PFs | G13: Mandatory unlisted-investment programme; ~10% to local SME/PE managers (Stimulus, Sanlam, Eos).
A14: Libya | B14: Social Security Fund of Libya | C14: Public PF | D14: 9000 | E14: 2023 | F14: Large but mostly domestic | G14: Limited alts beyond domestic bank deposits and real estate.
A15: Morocco | B15: CNSS Morocco | C15: Public PF | D15: 8500 | E15: 2024 | F15: Large allocator | G15: Verify recent allocations under post-2020 reform.
... A38: Tunisia | B38: CNRPS | C38: Civil-service PF | D38: 2200 | E38: 2023 | F38: Largest Tunisian PF | G38: Limited disclosure; verify.
A39: Egypt | B39: TSFE see above | C39: — | D39: 0 | E39: — | F39: (duplicate) | G39: —
A40: Rwanda | B40: RSSB | C40: Public PF | D40: 1500 | E40: 2024 | F40: Largest Rwandan PF | G40: Active in Rwandan strategic investments; has equity stakes in BK Group, Rwandair, etc.
A41: Tunisia | B41: CNSS Tunisia | C41: Public PF | D41: 1500 | E41: 2023 | F41: Major Tunisian PF | G41: Limited disclosure.
A42: Algeria | B42: CNAS Algeria | C42: Public PF | D42: 1500 | E42: 2023 | F42: Major Algerian PF | G42: Limited disclosure.
A43: Ethiopia | B43: POSSA | C43: Private-sector PF | D43: 1500 | E43: 2024 | F43: Major Ethiopian PF | G43: Verify any non-government allocation.
A44: Senegal | B44: FONSIS | C44: SWF (strategic) | D44: 1000 | E44: 2023 | F44: Active strategic investor in Senegal | G44: Direct equity in hotels, agribusiness, infra; co-invests with DFIs and African PE funds.
A45: Gabon | B45: FGIS | C45: SWF (strategic) | D45: 1500 | E45: 2023 | F45: Active strategic SWF in Central Africa | G45: Stakes in Gabonese financial sector and Africa-focused infra platforms.
A46: Djibouti | B46: FSD | C46: SWF (strategic) | D46: 1500 | E46: 2024 | F46: Newer but active strategic SWF | G46: Mandate includes domestic strategic investments and partnerships.
A47: Morocco | B47: Ithmar Capital | C47: SWF (sector-strategic) | D47: 1000 | E47: 2023 | F47: Tourism/renewables strategic SWF | G47: Co-investor with Green Africa Investment, AfDB, Morocco's Mohammed VI Fund.
A48: Nigeria | B48: Premium Pension | C48: PFA | D48: 1500 | E48: 2024 | F48: Top Nigerian PFA | G48: PenCom Multi-Fund Structure permits alts; verify commitments.
A49: Nigeria | B49: Sigma / Access Pensions | C49: PFA | D49: 1100 | E49: 2024 | F49: Top Nigerian PFA | G49: Access Holdings ownership; verify intra-group alts.
A50: Nigeria | B50: Tangerine APT Pensions | C50: PFA | D50: 1200 | E50: 2024 | F50: Top Nigerian PFA | G50: Post-merger entity; verify commitments.
A51: Morocco | B51: Mohammed VI Fund for Investment | C51: SWF (strategic) | D51: 4500 | E51: 2024 | F51: Newer but well-capitalised | G51: Anchor investor in domestic sectoral funds and PPP platforms.

Sheet Commitments Database
A1: Allocator (institution) | B1: Allocator country | C1: Allocator type | D1: Commitment type | E1: GP or counterparty | F1: Fund / Vehicle / Deal name | G1: Asset class | H1: Geographic focus | I1: Vintage / Year | J1: Commitment size (reported) | K1: Currency | L1: Disclosure type | M1: Source (short) | N1: Confidence | O1: Notes
A2: PIC (mgr for GEPF) | B2: South Africa | C2: Public PF (via mgr) | D2: Fund LP | E2: Africa50 | F2: Africa50 (shareholder stake) | G2: Infrastructure platform | H2: Pan-Africa | I2: 2025 | J2: USD 40m | K2: USD | L2: Press release | M2: Africa50 announcement Apr 2025 | N2: H | O2: PIC became 36th shareholder of Africa50 with USD 40m investment, signalling continental infrastructure commitment.
A3: PIC (mgr for GEPF) | B3: South Africa | C3: Public PF (via mgr) | D3: Fund LP | E3: Helios Investment Partners | F3: Helios Investors II / III / IV (historical) | G3: PE | H3: Pan-Africa | I3: 2009–2020 | J3: Not disclosed publicly | K3: USD | L3: Trade press / GP disclosure | M3: Helios LP composition; widely reported | N3: M | O3: PIC has been a recurring LP in Helios funds dating back to Helios II; specific commitment sizes not publicly disclosed.
A4: PIC (mgr for GEPF) | B4: South Africa | C4: Public PF (via mgr) | D4: Fund LP | E4: Pembani Remgro | F4: Pembani Remgro Infrastructure Fund | G4: Infrastructure | H4: Pan-Africa | I4: 2015 | J4: USD ~250m (anchor) | K4: USD | L4: Trade press | M4: Africa Capital Digest reporting | N4: M | O4: PIC was an anchor LP at fund formation.
A5: PIC (mgr for GEPF) | B5: South Africa | C5: Public PF (via mgr) | D5: Fund LP | E5: Convergence Partners | F5: Convergence Partners Communications Infrastructure Fund | G5: Infrastructure | H5: Pan-Africa | I5: various | J5: Not disclosed publicly | K5: USD | L5: Trade press | M5: AVCA fund close reporting | N5: M | O5: PIC participated in Convergence Partners' digital infrastructure platform.
A6: PIC (mgr for GEPF) | B6: South Africa | C6: Public PF (via mgr) | D6: Direct equity | E6: — | F6: Isibaya developmental investments portfolio | G6: Direct / Mixed | H6: Domestic + Africa | I6: ongoing | J6: ZAR ~70bn cumulative | K6: ZAR | L6: Annual report | M6: PIC Corporate Plan 2025/26 | N6: H | O6: Isibaya programme deploys to unlisted equity and infrastructure across SA and rest of Africa; PIC reports ~20% to alternatives overall.
A7: Eskom Pension and Provident Fund (EPPF) | B7: South Africa | C7: Parastatal PF | D7: Fund LP | E7: Multiple SA + pan-Africa GPs | F7: Multiple PE funds | G7: PE | H7: South Africa + Pan-Africa | I7: 10+ years history | J7: ~4% of AUM | K7: ZAR | L7: Top1000funds.com profile / EPPF disclosure | M7: EPPF investment strategy | N7: H | O7: EPPF has been investing in PE for 10+ years; ~10% to alts total, ~4% to PE; selectively includes pan-Africa funds.
A8: GEPF (via PIC) | B8: South Africa | C8: Public PF (via mgr) | D8: Platform | E8: African Development Bank | F8: Africa50 (indirect via PIC) | G8: Infrastructure platform | H8: Pan-Africa | I8: 2025 | J8: USD 40m (via PIC) | K8: USD | L8: Press release | M8: Africa50 announcement | N8: H | O8: GEPF is ultimate asset owner; PIC executes.
A9: Nigeria Sovereign Investment Authority (NSIA) | B9: Nigeria | C9: SWF (3 sub-funds) | D9: Fund LP | E9: Africa50 | F9: Africa50 Infrastructure Acceleration Fund (IAF) | G9: Infrastructure | H9: Pan-Africa | I9: 2026 | J9: Not disclosed | K9: USD | L9: Press release | M9: NSIA announcement Feb 2026 | N9: H | O9: Latest committed fund LP investment; aligns with NIF sub-fund mandate.
A10: Nigeria Sovereign Investment Authority (NSIA) | B10: Nigeria | C10: SWF (3 sub-funds) | D10: Direct equity | E10: Various consortia | F10: Nigeria Infrastructure Fund (NIF) direct deals | G10: Direct / Infrastructure | H10: Domestic | I10: ongoing | J10: USD 550m+ added FY24 | K10: USD | L10: Press release / annual report | M10: NSIA disclosure on additional govt funding | N10: H | O10: Federal Government injected USD 550m to scale energy infra; NIF is the direct-deal vehicle.
A11: Nigeria Sovereign Investment Authority (NSIA) | B11: Nigeria | C11: SWF | D11: Direct equity | E11: — | F11: Lekki Deep Sea Port (PPP equity) | G11: Direct / Infrastructure | H11: Domestic | I11: 2017– | J11: Not disclosed | K11: USD | L11: Annual report / trade press | M11: NSIA NIF portfolio disclosures | N11: H | O11: Notable NIF direct PPP equity stake.
A12: Nigeria Sovereign Investment Authority (NSIA) | B12: Nigeria | C12: SWF | D12: Direct equity | E12: — | F12: Pandagric Novum (agribusiness) | G12: Direct / Agribusiness | H12: Domestic | I12: 2018– | J12: Not disclosed | K12: USD | L12: Annual report | M12: NSIA NIF portfolio | N12: H | O12: NIF agribusiness anchor investment.
A13: Nigeria Sovereign Investment Authority (NSIA) | B13: Nigeria | C13: SWF | D13: Fund LP | E13: African Capital Alliance (ACA) | F13: Capital Alliance Private Equity (CAPE) funds | G13: PE | H13: West Africa / Nigeria | I13: various | J13: Not disclosed publicly | K13: USD | L13: Trade press / industry knowledge | M13: Industry reporting | N13: M | O13: NSIA has been an LP in Nigerian-focused PE funds; sizes not disclosed.
A14: Multiple Nigerian PFAs (consortium) | B14: Nigeria | C14: PFA cohort | D14: Fund LP | E14: ARM-Harith Infrastructure Investment | F14: ARM-Harith Infrastructure Fund I | G14: Infrastructure | H14: Nigeria | I14: 2015 | J14: USD ~30m raised total (mostly local pensions) | K14: USD/NGN | L14: Press release / trade press | M14: First fund local-pension participation | N14: H | O14: Landmark first Nigerian-pension-funded infra fund.
A15: Stanbic IBTC Pension Managers | B15: Nigeria | C15: PFA | D15: Fund LP | E15: Various Nigerian PE/infra GPs | F15: Multiple funds | G15: PE / Infrastructure | H15: Nigeria / West Africa | I15: various 2014–2024 | J15: Not disclosed at fund level | K15: NGN | L15: PenCom returns / trade press | M15: PenCom Multi-Fund disclosures | N15: M | O15: Largest PFA; alts are growing portion of portfolio under Multi-Fund Structure but per-fund sizes are not publicly disclosed.
A16: ARM Pension Managers (Access ARM Pensions) | B16: Nigeria | C16: PFA | D16: Fund LP | E16: ARM-Harith Infrastructure Investment | F16: ARM-Harith funds (intra-group affiliate) | G16: Infrastructure | H16: Nigeria | I16: various | J16: Not disclosed publicly | K16: NGN | L16: Industry reporting | M16: ARM group disclosures | N16: M | O16: ARM Pension and ARM-Harith are part of the same group; intra-group LP commitments are an obvious starting point.
A17: The Sovereign Fund of Egypt (TSFE) | B17: Egypt | C17: SWF (strategic) | D17: Co-investment | E17: B Investments | F17: EZ International (El-Ezaby Pharmacy logistics JV) | G17: Direct / Healthcare | H17: Domestic | I17: 2024 | J17: Not disclosed | K17: EGP | L17: Press release | M17: TSFE Healthcare & Pharma Subfund announcement | N17: H | O17: Co-invested via Healthcare & Pharma Subfund with B Investments and El-Ezaby Pharmacy.
A18: The Sovereign Fund of Egypt (TSFE) | B18: Egypt | C18: SWF (strategic) | D18: Platform | E18: ADQ (UAE) | F18: TSFE-ADQ Egyptian Health Platform | G18: Direct / Healthcare | H18: Domestic | I18: 2022– | J18: USD ~2bn (platform) | K18: USD | L18: Press release | M18: ADQ-TSFE healthcare platform | N18: H | O18: Strategic healthcare platform co-developed with ADQ.
A19: The Sovereign Fund of Egypt (TSFE) | B19: Egypt | C19: SWF (strategic) | D19: Platform | E19: Saudi PIF / Qatari QIA / ADQ | F19: Various Gulf-Egypt platforms | G19: Direct / Mixed | H19: Domestic | I19: ongoing | J19: Multi-bn | K19: USD | L19: Press release | M19: Repeated Gulf SWF co-investment announcements | N19: H | O19: TSFE has been the on-ground co-investment vehicle for Gulf SWF deployment into Egypt across financial services, healthcare, infra.
A20: Caisse de Dépôt et de Gestion (CDG) | B20: Morocco | C20: Sovereign + pension manager | D20: Direct equity | E20: — | F20: Fipar-Holding (CDG Invest) | G20: Direct / Diversified | H20: Domestic | I20: ongoing | J20: MAD multi-bn | K20: MAD | L20: Annual report | M20: CDG Group annual report | N20: H | O20: CDG Invest's direct-equity portfolio of Moroccan corporate stakes.
A21: Caisse de Dépôt et de Gestion (CDG) | B21: Morocco | C21: Sovereign + pension manager | D21: Fund GP (manage) | E21: CDG Invest (self) | F21: CapMezzanine III | G21: Private credit / Mezz | H21: Domestic | I21: active | J21: Not separately disclosed | K21: MAD | L21: Annual report | M21: CDG Capital materials | N21: H | O21: CDG Invest manages CapMezzanine III, a mezzanine fund for Moroccan SMEs.
A22: Caisse de Dépôt et de Gestion (CDG) | B22: Morocco | C22: Sovereign + pension manager | D22: Fund GP (manage) | E22: CDG Invest (self) | F22: InfraMaroc | G22: Infrastructure | H22: Domestic | I22: active | J22: Not separately disclosed | K22: MAD | L22: Annual report | M22: CDG Capital materials | N22: H | O22: CDG-managed infra investment vehicle.
A23: Caisse de Dépôt et de Gestion (CDG) | B23: Morocco | C23: Sovereign + pension manager | D23: Fund LP | E23: Mediterrania Capital Partners | F23: Mediterrania Capital II/III (historical) | G23: PE | H23: North Africa / pan-Africa | I23: various | J23: Not disclosed publicly | K23: EUR | L23: Trade press | M23: Industry coverage | N23: M | O23: CDG has historically been an LP in Mediterrania PE funds focused on Maghreb mid-market.
A24: Caisse de Dépôt et de Gestion (CDG) | B24: Morocco | C24: Sovereign + pension manager | D24: Direct equity | E24: IFC + Fipar-Holding | F24: Retail Holding (food distribution, Morocco + Côte d'Ivoire) | G24: Direct / Consumer | H24: Regional | I24: 2024 | J24: Not disclosed | K24: USD | L24: Press release | M24: IFC announcement 2024 | N24: H | O24: Joint investment with IFC and Fipar-Holding in retail/food platform.
A25: Ithmar Capital | B25: Morocco | C25: SWF (sector-strategic) | D25: Fund LP | E25: Wessal Capital | F25: Wessal Capital (joint Morocco + Gulf SWFs platform) | G25: Direct / Real estate, infra | H25: Domestic | I25: active | J25: USD 2.5bn target | K25: USD | L25: Press release | M25: Wessal Capital announcements | N25: H | O25: Joint platform with Abu Dhabi, Kuwait, Qatar SWFs.
A26: Mohammed VI Fund for Investment | B26: Morocco | C26: SWF (strategic) | D26: Fund LP / Anchor | E26: Multiple Moroccan sectoral GPs | F26: Sectoral co-investment funds | G26: Mixed | H26: Domestic | I26: active | J26: MAD 45bn capitalisation | K26: MAD | L26: Press release | M26: Mohammed VI Fund framework | N26: M | O26: Newly-capitalised; intended as anchor for Moroccan sectoral funds.
A27: Government Institutions Pension Fund (GIPF) | B27: Namibia | C27: Public PF | D27: Fund LP (multiple) | E27: 41 unique fund managers | F27: 77 indirect funds (covering PE, VC, private credit, infra, RE) | G27: PE / VC / Infra / Private credit / RE | H27: Mostly Namibia + Africa | I27: to 30 June 2025 | J27: N$24.9bn committed / N$22.8bn invested | K27: NAD | L27: Annual report / NAMFISA filing | M27: GIPF unlisted-investments disclosures 2024/25 | N27: H | O27: GIPF Unlisted Investment Policy mandates ~10% PE + 5% RE; 307 underlying companies.
A28: Government Institutions Pension Fund (GIPF) | B28: Namibia | C28: Public PF | D28: Fund LP | E28: Stimulus Investments | F28: Stimulus Investments Funds | G28: PE / Mezz | H28: Domestic (Namibia) | I28: multiple vintages | J28: N$ multiple commitments | K28: NAD | L28: GP disclosures + industry knowledge | M28: Stimulus Investments materials | N28: H | O28: Stimulus is a flagship Namibian unlisted manager; GIPF is an anchor LP.
A29: Government Institutions Pension Fund (GIPF) | B29: Namibia | C29: Public PF | D29: Fund LP | E29: Eos Capital | F29: Eos Capital funds (Allegrow, Euphrates, etc.) | G29: PE | H29: Domestic (Namibia) | I29: multiple vintages | J29: N$ multiple commitments | K29: NAD | L29: GP disclosures | M29: Eos Capital materials | N29: H | O29: Eos manages multiple unlisted funds anchored by GIPF.
A30: Government Institutions Pension Fund (GIPF) | B30: Namibia | C30: Public PF | D30: Fund LP | E30: Old Mutual Investment Group Namibia | F30: OMIGNAM unlisted programmes | G30: PE / Infrastructure | H30: Domestic (Namibia) | I30: multiple | J30: Not separately disclosed | K30: NAD | L30: GP disclosures | M30: OMIGNAM materials | N30: H
A31: Government Institutions Pension Fund (GIPF) | B31: Namibia | C31: Public PF | D31: Direct equity | E31: — | F31: Housing financing programme | G31: Direct / Housing infrastructure | H31: Domestic | I31: ongoing | J31: N$900m valued | K31: NAD | L31: Annual report | M31: GIPF disclosures | N31: H | O31: Domestic housing facility — a developmental-investment direct programme.
A32: Botswana Public Officers Pension Fund (BPOPF) | B32: Botswana | C32: Public PF | D32: Fund LP | E32: Aleyo Capital | F32: Aleyo Capital Fund I | G32: PE | H32: Domestic | I32: 2017 | J32: BWP 500m (USD ~43m) | K32: BWP | L32: Press release | M32: BPOPF private equity incubation programme | N32: H | O32: Part of BPOPF's domestic PE incubation programme.
A33: Botswana Public Officers Pension Fund (BPOPF) | B33: Botswana | C33: Public PF | D33: Fund LP | E33: Africa Lighthouse Capital | F33: Africa Lighthouse Capital Fund I | G33: PE | H33: Domestic + regional | I33: 2017 | J33: BWP 500m (USD ~43m) | K33: BWP | L33: Press release | M33: BPOPF private equity incubation programme | N33: H | O33: Part of BPOPF's incubation programme; anchor LP.
A34: Botswana Public Officers Pension Fund (BPOPF) | B34: Botswana | C34: Public PF | D34: Fund LP | E34: Vantage Capital | F34: Vantage Capital Mezzanine funds | G34: Private credit / Mezz | H34: Pan-Africa | I34: various | J34: Not disclosed publicly | K34: USD | L34: Trade press | M34: Industry reporting | N34: M | O34: Disclosed in industry sources; sizes not public.
A35: Botswana Public Officers Pension Fund (BPOPF) | B35: Botswana | C35: Public PF | D35: Fund LP | E35: Multiple SA + pan-Africa GPs | F35: Various | G35: PE / Infrastructure | H35: Pan-Africa | I35: ongoing | J35: ~10% of AUM target | K35: BWP | L35: BPOPF investments page | M35: BPOPF disclosures | N35: H | O35: BPOPF targets ~10% in alternatives including PE, infra, RE.
A36: NSSF Uganda | B36: Uganda | C36: Public PF | D36: Fund LP | E36: Pearl Capital Partners | F36: Yield Uganda Investment Fund | G36: PE / Agribusiness | H36: Domestic | I36: 2017 | J36: EUR ~2m founding (NSSF actually 2m, not 12m as initially recorded; 12m was total first close incl. EU/IFAD 10m) | K36: EUR | L36: Press release / annual report | M36: Yield Uganda Investment Fund disclosures | N36: H | O36: NSSF Uganda was a founding LP alongside EU and IFAD; fund now at EUR 20m total commitments. [CORRECTED in Phase 6: NSSF Uganda's actual founding ticket was EUR 2m, alongside EUR 10m from EU/IFAD, for the EUR 12m total first close. Fund subsequently grew to EUR 20m via FCA Investments + Soros Economic Development Fund.]
A37: NSSF Uganda | B37: Uganda | C37: Public PF | D37: Direct / Multiple | E37: Various | F37: ~20% alternatives portfolio (mostly RE, growing infra/PE) | G37: Mixed | H37: Domestic + EAC | I37: ongoing | J37: ~USh5.2tn (20% of USh26tn AUM) | K37: UGX | L37: Annual report | M37: NSSF Uganda Integrated Report | N37: H | O37: NSSF Uganda discloses ~20% alts; real estate dominant historically, infra/PE growing.
A38: NSSF Uganda | B38: Uganda | C38: Public PF | D38: Fund LP | E38: Catalyst Principal Partners (historical) | F38: Catalyst Fund II | G38: PE | H38: East Africa | I38: 2017 | J38: Not separately disclosed | K38: USD | L38: Trade press | M38: AVCA fund close coverage | N38: M | O38: Reported among Catalyst II's LPs.
A39: Fundo Soberano de Angola (FSDEA) | B39: Angola | C39: SWF | D39: Platform / Anchor | E39: Gemcorp Capital | F39: Gemcorp-FSDEA Pan-African Infrastructure Fund | G39: Infrastructure | H39: Pan-Africa | I39: 2024 | J39: USD ~500m target | K39: USD | L39: Press release | M39: AltAssets reporting | N39: H | O39: Joint pan-African infra fund with Gemcorp.
A40: Fundo Soberano de Angola (FSDEA) | B40: Angola | C40: SWF | D40: Direct / Co-invest | E40: Government consortium | F40: Lobito Corridor partnership | G40: Direct / Infrastructure | H40: Regional (Angola-Zambia-DRC) | I40: 2024 | J40: USD 1bn partnership | K40: USD | L40: Press release | M40: Lobito Corridor announcement | N40: H | O40: Multi-party rail-and-port infrastructure development.
A41: Fundo Soberano de Angola (FSDEA) | B41: Angola | C41: SWF | D41: Fund LP (multi) | E41: Various | F41: Diversified portfolio incl. private equity funds | G41: PE / Mixed | H41: Global + Africa | I41: ongoing | J41: Part of USD 3.9bn AUM (Dec 2024) | K41: USD | L41: Annual report | M41: FSDEA / IFSWF disclosures | N41: M | O41: FSDEA portfolio includes PE funds among other asset classes; per-fund detail not publicly disclosed.
A42: FONSIS | B42: Senegal | C42: SWF (strategic) | D42: Fund LP | E42: SEAF (Small Enterprise Assistance Funds) | F42: Oyass Capital | G42: PE / SME | H42: Domestic | I42: 2024 | J42: XOF 50bn (~USD 82m) | K42: XOF | L42: Press release | M42: FONSIS announcement Jan 2024 | N42: H | O42: FONSIS partnered with KfW (Germany) to launch Oyass Capital for Senegalese SMEs; awarded mgmt mandate to SEAF after intl tender.
A43: FONSIS | B43: Senegal | C43: SWF (strategic) | D43: Direct / Co-invest | E43: Multiple | F43: Strategic projects portfolio (Teyliom Industries, agribusiness, hospitality) | G43: Direct | H43: Domestic | I43: ongoing | J43: Not separately disclosed | K43: XOF | L43: FONSIS annual report | M43: FONSIS portfolio disclosures | N43: H | O43: FONSIS's primary mandate is direct strategic investment in Senegalese transformational projects.
A44: Agaciro Development Fund (AgDF) | B44: Rwanda | C44: SWF / Strategic | D44: Direct equity | E44: — | F44: Domestic strategic investments | G44: Direct | H44: Domestic | I44: ongoing | J44: Part of USD 220m AUM | K44: RWF | L44: Annual report | M44: AgDF disclosures | N44: M | O44: AgDF holds equity in selected Rwandan strategic companies.
A45: Rwanda Social Security Board (RSSB) | B45: Rwanda | C45: Public PF | D45: Direct equity | E45: — | F45: BK Group, RwandAir, other strategic stakes | G45: Direct | H45: Domestic | I45: ongoing | J45: Not separately disclosed | K45: RWF | L45: Annual report | M45: RSSB disclosures | N45: H | O45: RSSB holds significant direct equity in Rwandan strategic enterprises.
A46: Social Security and National Insurance Trust (SSNIT) | B46: Ghana | C46: Public PF | D46: Direct / Mixed alts | E46: Various | F46: Alternatives portfolio (real estate, PE, direct equity) | G46: PE / RE / Direct | H46: Domestic | I46: 2023 | J46: GHS 2.1bn (34% of GHS 16.7bn) | K46: GHS | L46: Annual report | M46: SSNIT 2022/23 Annual Report | N46: H | O46: 34% of portfolio in alts as of 2023; 2024 strategy shift to rebalance toward fixed income announced.
A47: Social Security and National Insurance Trust (SSNIT) | B47: Ghana | C47: Public PF | D47: Direct equity | E47: — | F47: Direct stakes in Ghanaian banks, agribusiness, real estate | G47: Direct | H47: Domestic | I47: ongoing | J47: Significant portion of equity portfolio | K47: GHS | L47: Annual report | M47: SSNIT disclosures | N47: H | O47: Significant historic direct-equity holdings in listed and unlisted Ghanaian firms.
A48: Ghana Infrastructure Investment Fund (GIIF) | B48: Ghana | C48: SWF (infra) | D48: Direct / Co-invest | E48: Various | F48: Domestic infrastructure deals (toll roads, energy, water) | G48: Direct / Infra | H48: Domestic | I48: ongoing | J48: Part of USD 400m AUM | K48: USD | L48: Annual report | M48: GIIF disclosures | N48: M | O48: Domestic infrastructure direct-deal mandate.
A49: FGIS | B49: Gabon | C49: SWF (strategic) | D49: Direct equity | E49: — | F49: Gabonese financial and infra stakes | G49: Direct / Mixed | H49: Domestic + regional | I49: ongoing | J49: Not separately disclosed | K49: XAF | L49: Annual report | M49: FGIS disclosures | N49: M | O49: FGIS has built equity stakes in Gabonese banking and infrastructure.
A50: FSD Djibouti | B50: Djibouti | C50: SWF (strategic) | D50: Co-invest / Platform | E50: Various | F50: Domestic strategic partnerships | G50: Direct / Infra | H50: Domestic | I50: ongoing | J50: Not separately disclosed | K50: USD | L50: Press releases | M50: FSD disclosures | N50: M | O50: Mandate includes strategic co-investments.
A51: Axis Pension Trust | B51: Ghana | C51: Tier 2/3 corporate trustee | D51: Fund LP / Co-investor | E51: Growth Investment Partners (GIP) – BII platform | F51: Growth Investment Partners Ghana | G51: Private credit / SME debt | H51: Domestic (Ghana) | I51: 2026 | J51: USD 5m | K51: USD | L51: Press release / trade press | M51: BII / Axis Pension Trust / Norfund joint announcement April 2026 | N51: H | O51: First disclosed Ghanaian pension trustee commitment to SME debt under Ghana's new 5% alternative-assets rule. Co-committed alongside Norfund (USD 15m); GIP capital base raised to ~USD 70m.
A52: Axis Pension Trust | B52: Ghana | C52: Tier 2/3 corporate trustee | D52: Fund LP | E52: Savannah Impact Advisory (Manager) | F52: Ci Gaba Fund of Funds | G52: Fund of funds (PE / VC / Private credit) | H52: Ghana + Nigeria + Senegal + Côte d'Ivoire | I52: 2026 | J52: Share of GHS 383m (USD 35m) first close | K52: GHS | L52: Press release / trade press | M52: Ci Gaba FoF first close March 2026 | N52: H | O52: Ghanaian pension capital is >2/3 of Ci Gaba's first-close commitments. West Africa's first domestically-domiciled private fund of funds; target size GHS 1bn / USD 91m.
A53: Enterprise Trustees Limited | B53: Ghana | C53: Tier 2/3 corporate trustee | D53: Fund LP | E53: Savannah Impact Advisory (Manager) | F53: Ci Gaba Fund of Funds | G53: Fund of funds (PE / VC / Private credit) | H53: Ghana + Nigeria + Senegal + Côte d'Ivoire | I53: 2026 | J53: Share of GHS 383m (USD 35m) first close | K53: GHS | L53: Press release / trade press | M53: Ci Gaba FoF first close March 2026 | N53: H | O53: One of Ghana's largest private trustees; LP alongside AXIS, Stanbic IMS, CAL Asset Management, FSDAi, Small Foundation, FMO.
A54: PIC (South Africa) | B54: South Africa | C54: Public PF (via mgr) | D54: Direct equity (shareholder) | E54: Africa Finance Corporation (AFC) | F54: AFC equity stake | G54: Infrastructure / Multilateral | H54: Pan-Africa | I54: 2022 | J54: USD 100m | K54: USD | L54: Press release | M54: AFC announcement of PIC $100m equity investment Dec 2022 | N54: H | O54: Separate from the 2025 PIC-Africa50 commitment. PIC's largest disclosed pan-African institutional equity position.
A55: Seychelles Pension Fund | B55: Seychelles | C55: Public PF | D55: Direct equity (shareholder) | E55: Africa Finance Corporation (AFC) | F55: AFC equity stake | G55: Infrastructure / Multilateral | H55: Pan-Africa | I55: various | J55: Part of USD 35.5m group commitment | K55: USD | L55: Press release | M55: AFC press release on Indian Ocean shareholders | N55: H | O55: First Indian Ocean shareholder of AFC; joined with Sierra Leone and GIIF Ghana.
A56: Ghana Infrastructure Investment Fund (GIIF) | B56: Ghana | C56: SWF (infra) | D56: Direct equity (shareholder) | E56: Africa Finance Corporation (AFC) | F56: AFC equity stake | G56: Infrastructure / Multilateral | H56: Pan-Africa | I56: various | J56: Part of USD 35.5m group commitment | K56: USD | L56: Press release | M56: AFC press release on Ghana/Sierra Leone/Seychelles shareholders | N56: H | O56: GIIF deploys its own balance sheet into AFC; aligns with GIIF's domestic-infra mandate.
A57: National Pension Fund (NPF) Mauritius | B57: Mauritius | C57: Public PF | D57: Direct equity (shareholder) | E57: Africa Finance Corporation (AFC) | F57: AFC equity stake | G57: Infrastructure / Multilateral | H57: Pan-Africa | I57: various | J57: Not separately disclosed | K57: USD | L57: Press release | M57: AFC press release on Côte d'Ivoire / Mauritius shareholders | N57: H | O57: Mauritius participates via NPF and NSF jointly.
A58: National Savings Fund (NSF) Mauritius | B58: Mauritius | C58: Public PF | D58: Direct equity (shareholder) | E58: Africa Finance Corporation (AFC) | F58: AFC equity stake | G58: Infrastructure / Multilateral | H58: Pan-Africa | I58: various | J58: Not separately disclosed | K58: USD | L58: Press release | M58: AFC press release on Mauritius shareholders | N58: H | O58: Joint Mauritian participation alongside NPF.
A59: CNPS Cameroon | B59: Cameroon | C59: Public PF | D59: Direct equity (shareholder) | E59: Africa Finance Corporation (AFC) | F59: AFC equity stake | G59: Infrastructure / Multilateral | H59: Pan-Africa | I59: various | J59: Not separately disclosed | K59: USD | L59: Press release | M59: Business in Cameroon — CNPS Cameroon joins AFC as shareholder | N59: H | O59: First Central African pension fund to take AFC equity. Important precedent for CIPRES-supervised funds.
A60: CDC Gabon (State pension fund of Gabon) | B60: Gabon | C60: Civil-service PF | D60: Direct equity (shareholder) | E60: Africa Finance Corporation (AFC) | F60: AFC equity stake | G60: Infrastructure / Multilateral | H60: Pan-Africa | I60: various | J60: Not separately disclosed | K60: USD | L60: Press release | M60: AFC equity-shareholder list | N60: H | O60: Distinct from CNSS Gabon and FGIS. NEW entity vs Phase 1 roster — should be added to Pension Funds tab.
A61: Government of Côte d'Ivoire | B61: Côte d'Ivoire | C61: Sovereign | D61: Direct equity (shareholder) | E61: Africa Finance Corporation (AFC) | F61: AFC equity stake | G61: Infrastructure / Multilateral | H61: Pan-Africa | I61: various | J61: Not separately disclosed | K61: USD | L61: Press release | M61: AFC press release on Côte d'Ivoire / Mauritius shareholders | N61: H | O61: Ivorian sovereign equity participation.
A62: Government of Sierra Leone | B62: Sierra Leone | C62: Sovereign | D62: Direct equity (shareholder) | E62: Africa Finance Corporation (AFC) | F62: AFC equity stake | G62: Infrastructure / Multilateral | H62: Pan-Africa | I62: various | J62: Part of USD 35.5m group commitment | K62: USD | L62: Press release | M62: AFC press release | N62: H
A63: Government of Egypt | B63: Egypt | C63: Sovereign | D63: Direct equity (shareholder) | E63: Africa Finance Corporation (AFC) | F63: AFC equity stake | G63: Infrastructure / Multilateral | H63: Pan-Africa | I63: 2024 | J63: Not separately disclosed | K63: USD | L63: Press release | M63: AFC – Egypt becomes first North African shareholder (2024) | N63: H | O63: First North African shareholder of AFC; widens TSFE-NOSI Egypt's institutional alts footprint outside the country.
A64: CDC Sénégal | B64: Senegal | C64: Civil-service PF / Sovereign | D64: Fund LP | E64: Africa50 | F64: Africa50 Infrastructure Acceleration Fund (IAF) | G64: Infrastructure | H64: Pan-Africa | I64: 2024 | J64: Part of USD 222.5m first close (>USD 275m mobilised) | K64: USD | L64: Press release | M64: Africa50 IAF first-close announcement | N64: H | O64: Distinct from FONSIS; Senegal's civil-service deposit institution. Africa50-IAF was named 'African first' as it was majority African-LP funded.
A65: CDC Benin | B65: Benin | C65: Civil-service PF / Sovereign | D65: Fund LP | E65: Africa50 | F65: Africa50 Infrastructure Acceleration Fund (IAF) | G65: Infrastructure | H65: Pan-Africa | I65: 2024 | J65: Part of Africa50-IAF first close | K65: USD | L65: Press release | M65: Africa50 IAF first-close announcement | N65: H | O65: Beninese deposit-and-investment institution joining Africa50-IAF.
A66: CNSS Togo | B66: Togo | C66: Public PF | D66: Fund LP | E66: Africa50 | F66: Africa50 Infrastructure Acceleration Fund (IAF) | G66: Infrastructure | H66: Pan-Africa | I66: 2024 | J66: Part of Africa50-IAF first close | K66: USD | L66: Press release | M66: Africa50 IAF first-close announcement | N66: H | O66: First disclosed CIPRES-zone pension fund LP commitment to a pan-African PE-style infrastructure fund.
A67: CDG Invest (Morocco) | B67: Morocco | C67: Sovereign (subsidiary of CDG) | D67: Fund LP | E67: Africa50 | F67: Africa50 Infrastructure Acceleration Fund (IAF) | G67: Infrastructure | H67: Pan-Africa | I67: 2024 | J67: Part of Africa50-IAF first close | K67: USD | L67: Press release | M67: Africa50 IAF first-close announcement | N67: H | O67: CDG Invest is the asset-management subsidiary of CDG Morocco.
A68: CBK Pension Fund (Kenya, Central Bank of Kenya) | B68: Kenya | C68: Occupational PF (central bank) | D68: Fund LP | E68: AfricInvest | F68: AfricInvest FIVE (Financial Inclusion Vehicle, evergreen) | G68: PE / Financial services | H68: Pan-Africa | I68: 2018 | J68: Not separately disclosed | K68: USD | L68: Press release | M68: AVCA – AfricInvest FIVE second close Oct 2018 announcement | N68: H | O68: CBK Pension Fund (Central Bank of Kenya staff pension) committed alongside Norfund and IFU. CBK PF remained LP through subsequent closes.
A69: NAPSA Zambia | B69: Zambia | C69: Public PF (mandatory) | D69: Direct equity (platform anchor) | E69: BII + Swedfund | F69: Growth Investment Partners Zambia (GIP Zambia) | G69: Private credit / SME debt | H69: Domestic (Zambia) | I69: 2025 | J69: USD 17.5m | K69: USD | L69: Press release | M69: BII launch of GIP Zambia Jan 2025 | N69: H | O69: NAPSA is the third anchor alongside BII (USD 37.5m) and Swedfund (USD 15m); GIP Zambia plans to deploy USD 300m over 15 years to ~150 Zambian SMEs in local currency. Largest single disclosed Zambian-pension alts commitment.
A70: Multiple Kenyan pension funds | B70: Kenya | C70: Pension fund cohort (unnamed) | D70: Fund LP | E70: Adenia Partners | F70: Adenia Capital V | G70: PE | H70: Pan-Africa | I70: 2024 | J70: Share of USD 470m hard cap close | K70: USD | L70: Trade press | M70: Adenia April 2024 fund-close press release; Africa Global Funds; Bloomberg coverage | N70: M | O70: Adenia Capital V LP roster includes 'Kenyan pension funds' but no specific funds named at close-disclosure level. Likely candidates: schemes that participate via KEPFIC consortium.
A71: Multiple Ghanaian pension funds | B71: Ghana | C71: Pension fund cohort (unnamed) | D71: Fund LP | E71: Adenia Partners | F71: Adenia Capital V | G71: PE | H71: Pan-Africa | I71: 2024 | J71: Share of USD 470m hard cap close | K71: USD | L71: Trade press | M71: Adenia April 2024 fund-close press release | N71: M | O71: Adenia Capital V LP roster includes 'Ghanaian pension funds' but no specific trustees named at close-disclosure level.
A72: PIC (South Africa) | B72: South Africa | C72: Public PF (via mgr) | D72: Fund LP | E72: Adenia Partners | F72: Adenia Capital V | G72: PE | H72: Pan-Africa | I72: 2024 | J72: Share of USD 470m hard cap close | K72: USD | L72: Trade press | M72: Adenia April 2024 fund-close press release | N72: H | O72: Specifically named as LP in Adenia V's hard-cap close; PIC commitment size not disclosed.
A73: Multiple East African pension funds (likely incl. NSSF Uganda) | B73: East Africa | C73: Pension fund cohort | D73: Fund LP | E73: Catalyst Principal Partners | F73: Catalyst Fund II | G73: PE | H73: East Africa + DRC | I73: 2016–2017 final close | J73: Share of USD 155m total close | K73: USD | L73: Trade press | M73: Catalyst Fund II close coverage; EIB profile | N73: M | O73: Catalyst Fund II disclosed 'local pension funds and family offices' as LPs alongside CDC/BII USD 30m, EIB, IFC, Proparco, Swedfund. NSSF Uganda is known to have committed (per earlier industry reporting); other names not publicly disclosed.
A74: KEPFIC (Kenya Pension Funds Investment Consortium) | B74: Kenya | C74: Pension consortium (24 funds) | D74: Pooled mandate / facilitated member investments | E74: Various | F74: KEPFIC-facilitated housing + infrastructure investments | G74: Infrastructure / Alts | H74: Domestic + Regional | I74: 2019– | J74: USD 113m mobilized into two housing projects; third road bond near closing (2023) | K74: USD | L74: Allocator disclosure | M74: IFC 2023 Pooling Pensions in Kenya; MiDA Lot 3 update | N74: H | O74: Retained as an aggregate consortium archetype only. IFC reports KEPFIC mobilized $113m into two housing projects and facilitated two member-fund investments, with a road infrastructure bond near closing. Individual KEPFIC member-only rows removed because membership alone is not allocator-to-vehicle commitment evidence.
A75: Kenya Power & Lighting Co. Pension Fund (KPLC PF) | B75: Kenya | C75: Occupational PF (parastatal) | D75: Fund LP | E75: Ascent Capital Africa | F75: Ascent Rift Valley Fund I (ARVF I) | G75: PE / SME growth | H75: East Africa (Kenya, Uganda, Ethiopia) | I75: 2014 | J75: USD 4m | K75: USD | L75: Press release / trade press | M75: Africa Global Funds — ARVF first close July 2014 (KPLC PF named as 'first pension fund in East African PE') | N75: H | O75: Historical first: described as 'the first pension fund in East African private equity'. ARVF I total first close USD 50m.
A76: Nation Media Group Staff Retirement Benefits Scheme (NMG Pension Fund) | B76: Kenya | C76: Corporate occupational PF | D76: Fund LP (via STANLIB) | E76: Ascent Capital Africa | F76: Ascent Rift Valley Fund I (ARVF I) | G76: PE / SME growth | H76: East Africa (Kenya, Uganda, Ethiopia) | I76: 2015 | J76: USD 1m (KES 91m) | K76: USD | L76: Press release | M76: Africa Global Funds — 'NMG Pension Fund commits $1m to Ascent' (25 Feb 2015) | N76: H | O76: Commitment made via STANLIB Kenya as fund manager. Trustee Wallace Kantai: 'first of many investments of this kind by our fund'.
A77: Kenya Power & Lighting Co. Pension Fund (KPLC PF) | B77: Kenya | C77: Occupational PF (parastatal) | D77: Fund LP | E77: Ascent Capital Africa | F77: Ascent Rift Valley Fund II (ARVF II) | G77: PE / SME growth | H77: East Africa (Kenya, Uganda, Ethiopia, Rwanda, Tanzania) | I77: various 2018-2020 | J77: Not separately disclosed (2 KPLC PF commitments per source) | K77: USD | L77: DFI co-disclosure | M77: BIO / IFC project disclosures; Africa Global Funds; AVCA Ascent interview | N77: H | O77: Source notes 'three pension funds (two from Kenya Power Pension Fund and one from Nation Media Group Staff Pension Fund)'. Two KPLC PF commitments likely reflect the KPLC main scheme + KPLC Staff Retirement Benefits Scheme separately.
A78: Nation Media Group Staff Retirement Benefits Scheme (NMG Pension Fund) | B78: Kenya | C78: Corporate occupational PF | D78: Fund LP | E78: Ascent Capital Africa | F78: Ascent Rift Valley Fund II (ARVF II) | G78: PE / SME growth | H78: East Africa | I78: various 2018-2020 | J78: Not separately disclosed | K78: USD | L78: DFI co-disclosure | M78: IFC ARVF II project disclosure; Africa Global Funds | N78: H | O78: Re-up after ARVF I; NMG remains an LP.
A79: Nigeria Sovereign Investment Authority (NSIA) | B79: Nigeria | C79: SWF (NIF sub-fund) | D79: Fund LP | E79: Sahel Capital | F79: Fund for Agricultural Finance in Nigeria (FAFIN) | G79: PE / Agribusiness | H79: Nigeria | I79: 2017 | J79: Share of USD 65.9m final close | K79: USD | L79: Press release | M79: NSIA Sahel Capital FAFIN final close announcement | N79: H | O79: NSIA was an LP alongside AfDB, CDC Group/BII, and Dutch Good Growth Fund (DGGF) in Sahel's FAFIN. NSIA's earliest disclosed PE fund LP position alongside DFIs.
A80: Nigerian PFAs (historical cohort) | B80: Nigeria | C80: PFA cohort | D80: Fund LP (historical) | E80: African Capital Alliance (ACA) | F80: CAPE I-IV (Capital Alliance Private Equity) | G80: PE | H80: Nigeria + West Africa | I80: 1998-ongoing | J80: Cumulative >USD 1bn raised across CAPE I-IV | K80: USD | L80: ACA disclosures / industry coverage | M80: ACA member interview and corporate site | N80: M | O80: ACA historically championed PE inclusion as allowable Nigerian pension asset class. Some PFA commitments to CAPE funds confirmed by ACA's stated 'institutional investor base, primarily pension funds and DFIs'; specific PFA names not individually disclosed.
A81: Rwanda Social Security Board (RSSB) | B81: Rwanda | C81: Public PF (mandatory) | D81: Fund LP (anchor) | E81: Enko Capital (Rwanda subsidiary) | F81: Rwanda SME Growth Fund | G81: PE / SME growth (local-currency) | H81: Rwanda | I81: 2026 | J81: USD 30m anchor (RWF equivalent) + USD 3m TA facility seed | K81: USD/RWF | L81: Press release | M81: FSDA — RSSB Anchors First Close of USD 100m Rwanda SME Fund (28 April 2026) | N81: H | O81: Three regional firsts per RSSB CEO Regis Rugemanshuro: (i) FIRST public pension-fund-led initiative focused exclusively on SME financing; (ii) FIRST permanent capital vehicle anchored by a pension fund; (iii) FIRST pension fund dedicating a TA facility in a fund. Fund target USD 100m. Enko Capital parent has USD 1.6bn AUM. FSDA structured the deal + potential guarantee facility.
A82: Asset Owners Forum of South Africa (AOFSA) | B82: South Africa | C82: Pension consortium (12-15 funds) | D82: Pooled mandate / aggregate member commitments | E82: Various (mandates allocated to managers) | F82: SA infrastructure + alts mandates | G82: Infrastructure / Alts | H82: Domestic + regional | I82: 2021-ongoing | J82: R5.7bn / USD 400m+ collectively committed | K82: USD/ZAR | L82: Allocator press release / Batseta / USAID + MiDA + World Bank | M82: Engineering News 2022; MiDA/USAID AOFSA case materials | N82: H | O82: Retained as an aggregate consortium archetype only. Public sources report actual collective AOFSA member commitments; individual member-only rows removed because the public evidence does not allocate the commitments by named member fund.
A83: Petra Trust Company (Ghana) | B83: Ghana | C83: Tier 2/3 corporate trustee | D83: Fund LP | E83: Mirepa Investment Advisors | F83: Mirepa Capital SME Fund I | G83: PE / SME growth | H83: Ghana | I83: 2023 | J83: Share of GHS 120m initial close | K83: GHS | L83: Press release | M83: Mirepa Investment Advisors press release / The Innovation Spark / B&FT | N83: H | O83: Second Ghana fund anchored solely by local investors (after Injaro IGVCF). Petra Trust named alongside Axis Pensions, VCTF, and CAMCOL schemes. Mirepa fund focuses on light manufacturing, technology, cleantech, agribusiness, healthcare, financial services.
A84: Axis Pension Trust | B84: Ghana | C84: Tier 2/3 corporate trustee | D84: Fund LP | E84: Mirepa Investment Advisors | F84: Mirepa Capital SME Fund I | G84: PE / SME growth | H84: Ghana | I84: 2023 | J84: Share of GHS 120m initial close | K84: GHS | L84: Press release | M84: Mirepa Investment Advisors press release | N84: H | O84: Axis Pensions named LP alongside Petra Trust, VCTF, CAMCOL schemes. Predates Axis's later commitments to GIP Ghana (Apr 2026) and Ci-Gaba FoF (Mar 2026).
A85: Multiple Ghanaian pension schemes (via CAL Asset Management — CAMCOL) | B85: Ghana | C85: Pension scheme cohort (via mgr) | D85: Fund LP (via manager) | E85: Mirepa Investment Advisors | F85: Mirepa Capital SME Fund I | G85: PE / SME growth | H85: Ghana | I85: 2023 | J85: Share of GHS 120m initial close | K85: GHS | L85: Press release | M85: Mirepa Investment Advisors press release | N85: M | O85: CAL Asset Management Company Limited (CAMCOL) is one of the major Ghanaian pension asset managers. Underlying pension scheme identities not individually disclosed.
A86: Multiple Ghanaian pension funds (Injaro anchor cohort) | B86: Ghana | C86: Pension fund cohort | D86: Fund LP (anchor) | E86: Injaro Investment Advisors | F86: Injaro Ghana Venture Capital Fund (IGVCF) | G86: PE / SME / VC | H86: Ghana + Côte d'Ivoire | I86: 2023 | J86: Share of GHS 216m (~USD 17.4m) final close (Dec 2023) | K86: GHS | L86: Press release | M86: AVCA — Injaro announces final close; Africa Global Funds; Africa PE News | N86: H | O86: FIRST Ghana fund of its kind anchored by local pension funds (per Injaro press release). Predates Mirepa I (2023) and Ci-Gaba (2026). Specific Ghanaian pension fund names not disclosed in public sources but precedent-setting.
A87: GEPF / PIC (South Africa) | B87: South Africa | C87: Public PF (via asset manager) | D87: Fund LP | E87: Zebu Investment Partners | F87: Africa Food Security Fund (AFSF) | G87: PE / agriculture / food security | H87: Sub-Saharan Africa | I87: 2019 | J87: Not disclosed; fund size USD 84m | K87: USD | L87: DFI / fund close announcement | M87: DGGF news release, Jan 2019 | N87: H | O87: DGGF names PIC on behalf of GEPF among first-round AFSF investors alongside AfDB, CDC Group/BII, DGGF, IFU, and EBID; Kuramo later joined, bringing fund commitments to USD 84m.

Sheet Pipeline & Mandates
A1: Entity / prospective allocator | B1: Allocator country | C1: Allocator type | D1: Status category | E1: GP or counterparty | F1: Fund / Vehicle / Deal name | G1: Asset class | H1: Geographic focus | I1: Vintage / Year | J1: Potential size / target | K1: Currency | L1: Disclosure type | M1: Source (short) | N1: Pipeline confidence | O1: Reason not in Commitments Database | P1: Source URL
A2: Multiple Nigerian PFAs (expected) | B2: Nigeria | C2: PFA cohort | D2: Expected follow-on | E2: ARM-Harith Infrastructure Investment | F2: ARM-Harith Climate and Transition Infrastructure Fund (ACT Fund) | G2: Infrastructure | H2: Nigeria + Africa | I2: 2025 | J2: Targeted GBP ~31m from pensions | K2: GBP/NGN | L2: Press release | M2: FSDAi GBP 10m catalytic commitment April 2025 | N2: M | O2: FSDAi commitment is structured to unlock pension contributions, but no named or closed PFA LP allocation is disclosed yet. | P2: https://archive.fsdafrica.org/arm-harith-and-fsd-africa-investments-announce-gbp-10m-commitment-to-unlock-nigerian-pension-funds-and-catalyse-local-capital-for-infrastructure/
A3: Multiple Nigerian institutional investors (incl. PFAs) | B3: Nigeria | C3: Mixed institutional cohort | D3: Targeted / eligible subscription | E3: Sahel Capital | F3: Sahel Agribusiness Private Debt Fund | G3: Private credit / Agribusiness | H3: Nigeria | I3: 2026-launched | J3: NGN 75bn target; NGN 25bn first phase | K3: NGN | L3: Launch announcement / trade press | M3: Ecofin Agency Feb 2026 | N3: M | O3: Subscription is open to qualified institutional investors including pension funds, but no actual PFA subscription or allocation is disclosed. | P3: https://www.ecofinagency.com/news-finances/2502-53253-nigerian-investment-firm-sahel-capital-launches-55-million-fund-to-narrow-farm-finance-gap
A4: NSSF Uganda | B4: Uganda | C4: Public PF (mandatory) | D4: Planned anchor | E4: TBD manager | F4: NSSF Uganda Fund of Funds (planned) | G4: FoF (PE/VC/Private credit) | H4: Uganda + EAC | I4: 2026 | J4: USD 15m+ planned anchor; USD 100m fund target | K4: USD | L4: Trade press | M4: ImpactAlpha planned FoF coverage Apr 2026 | N4: M | O4: Planned/prospective fund of funds; not a closed commitment as of the audit date.
A5: The Sovereign Fund of Egypt (TSFE) | B5: Egypt | C5: SWF (strategic) | D5: MoU / mandate | E5: BlackRock | F5: Climate / infra mandate | G5: Infrastructure | H5: Domestic | I5: ongoing | J5: Not disclosed | K5: USD | L5: Press release / MoU coverage | M5: BlackRock-TSFE MoU coverage | N5: M | O5: MoU/mandate announced; no specific fund commitment or allocation disclosed.
A6: Kenya Revenue Authority (KRA) Staff Pension Scheme | B6: Kenya | C6: Occupational PF (parastatal) | D6: Member-only mandate evidence | E6: KEPFIC consortium / multiple managers | F6: KEPFIC infrastructure + alts mandates | G6: Infrastructure / Alts | H6: Kenya + regional | I6: ongoing | J6: Part of KEPFIC aggregate member AUM | K6: KES | L6: KEPFIC member listing / IFC 2023 | M6: KEPFIC member evidence | N6: H | O6: Named KEPFIC member; membership is useful pipeline context but is not an individual allocator-to-vehicle commitment. | P6: https://www.ifc.org/en/stories/2023/pooling-pensions-in-kenya
A7: Safaricom Staff Pension Scheme | B7: Kenya | C7: Corporate occupational PF (telecoms) | D7: Member-only mandate evidence | E7: KEPFIC consortium / multiple managers | F7: KEPFIC infrastructure + alts mandates | G7: Infrastructure / Alts | H7: Kenya + regional | I7: ongoing | J7: Part of KEPFIC aggregate member AUM | K7: KES | L7: KEPFIC member listing | M7: KEPFIC member evidence | N7: H | O7: Named KEPFIC member; membership is useful pipeline context but is not an individual allocator-to-vehicle commitment. | P7: https://www.ifc.org/en/stories/2023/pooling-pensions-in-kenya
A8: KenGen Staff Retirement Benefits Scheme | B8: Kenya | C8: Occupational PF (parastatal) | D8: Member-only mandate evidence | E8: KEPFIC consortium | F8: KEPFIC infrastructure + alts mandates | G8: Infrastructure / Alts | H8: Kenya + regional | I8: ongoing | J8: Part of KEPFIC aggregate member AUM | K8: KES | L8: KEPFIC member listing | M8: KEPFIC member evidence | N8: H | O8: Named KEPFIC member; membership is useful pipeline context but is not an individual allocator-to-vehicle commitment. | P8: https://www.ifc.org/en/stories/2023/pooling-pensions-in-kenya
A9: Kenya Pipeline Company Staff Retirement Benefits Scheme | B9: Kenya | C9: Occupational PF (parastatal) | D9: Member-only mandate evidence | E9: KEPFIC consortium | F9: KEPFIC infrastructure + alts mandates | G9: Infrastructure / Alts | H9: Kenya + regional | I9: ongoing | J9: Part of KEPFIC aggregate member AUM | K9: KES | L9: KEPFIC member listing | M9: KEPFIC member evidence | N9: H | O9: Named KEPFIC member; membership is useful pipeline context but is not an individual allocator-to-vehicle commitment. | P9: https://www.ifc.org/en/stories/2023/pooling-pensions-in-kenya
A10: National Fund for Municipal Workers (NFMW) | B10: South Africa | C10: Multi-employer PF (local gov't) | D10: Member-only mandate evidence | E10: AOFSA consortium | F10: SA infrastructure mandates via AOFSA | G10: Infrastructure | H10: South Africa | I10: ongoing | J10: Part of AOFSA aggregate commitments | K10: ZAR | L10: AOFSA launch coverage / MiDA Advisors | M10: AOFSA member evidence | N10: H | O10: Named AOFSA member; public evidence supports aggregate AOFSA commitments but not a separate member-level commitment record. | P10: https://www.engineeringnews.co.za/article/aofsa-exceeds-infrastructure-investment-target-as-it-marks-first-anniversary-2022-11-21
A11: KwaZulu-Natal Joint Municipal Pension Fund (NJMPF) | B11: South Africa | C11: Public sector PF (KZN municipalities) | D11: Member-only mandate evidence | E11: AOFSA consortium | F11: SA infrastructure mandates via AOFSA | G11: Infrastructure | H11: South Africa | I11: ongoing | J11: Part of AOFSA aggregate commitments | K11: ZAR | L11: AOFSA launch coverage | M11: AOFSA member evidence | N11: H | O11: Named AOFSA member; public evidence supports aggregate AOFSA commitments but not a separate member-level commitment record. | P11: https://www.engineeringnews.co.za/article/aofsa-exceeds-infrastructure-investment-target-as-it-marks-first-anniversary-2022-11-21
A12: KZN Municipal Pension Fund | B12: South Africa | C12: Public sector PF (local gov't) | D12: Member-only mandate evidence | E12: AOFSA consortium | F12: SA infrastructure mandates via AOFSA | G12: Infrastructure | H12: South Africa | I12: ongoing | J12: Part of AOFSA aggregate commitments | K12: ZAR | L12: AOFSA launch coverage | M12: AOFSA member evidence | N12: H | O12: Named AOFSA member; public evidence supports aggregate AOFSA commitments but not a separate member-level commitment record. | P12: https://www.engineeringnews.co.za/article/aofsa-exceeds-infrastructure-investment-target-as-it-marks-first-anniversary-2022-11-21
A13: Motor Industry Retirement Fund (MIRF) | B13: South Africa | C13: Multi-employer PF (motor industry) | D13: Member-only mandate evidence | E13: AOFSA consortium | F13: SA infrastructure mandates via AOFSA | G13: Infrastructure | H13: South Africa | I13: ongoing | J13: Part of AOFSA aggregate commitments | K13: ZAR | L13: AOFSA launch coverage | M13: AOFSA member evidence | N13: H | O13: Named AOFSA member; public evidence supports aggregate AOFSA commitments but not a separate member-level commitment record. | P13: https://www.engineeringnews.co.za/article/aofsa-exceeds-infrastructure-investment-target-as-it-marks-first-anniversary-2022-11-21
A14: KEPFIC (Kenya Pension Funds Investment Consortium) | B14: Kenya | C14: Pension consortium / pooled mandate | D14: Pooled mandate / aggregate evidence | E14: Various managers via KEPFIC consortium | F14: KEPFIC pooled mandates (Kenya) | G14: Infrastructure / Alts | H14: Kenya + regional | I14: 2019-ongoing | J14: USD 113m mobilized into two housing projects; member AUM ~USD 5bn | K14: USD | L14: Aggregate consortium / pooled mandate | M14: IFC 2023; MiDA Advisors | N14: H | O14: Aggregate pooled mandate / consortium archetype, not a conventional fund vehicle LP row. Kept out of Fund Vehicles and Commitments Database to avoid treating a mandate platform as a fund commitment. | P14: https://www.ifc.org/en/stories/2023/pooling-pensions-in-kenya ; https://www.midaadvisors.com/advisory-firm-financing-the-development-of-critical-infrastructure-in-kenya-with-local-institutional-capital
A15: Asset Owners Forum of South Africa (AOFSA) | B15: South Africa | C15: Pension consortium / pooled mandate | D15: Pooled mandate / aggregate evidence | E15: Various managers via AOFSA consortium | F15: AOFSA pooled infrastructure mandates (South Africa) | G15: Infrastructure / Alts | H15: South Africa | I15: 2021-ongoing | J15: R5.7bn / USD 400m+ collectively committed to infrastructure and other alternatives | K15: ZAR / USD | L15: Aggregate consortium / pooled mandate | M15: Engineering News 2022; MiDA/USAID AOFSA case materials | N15: H | O15: Aggregate pooled mandate / consortium archetype, not a conventional fund vehicle LP row. Kept out of Fund Vehicles and Commitments Database to avoid treating a mandate platform as a fund commitment. | P15: https://www.engineeringnews.co.za/article/aofsa-exceeds-infrastructure-investment-target-as-it-marks-first-anniversary-2022-11-21 ; https://www.midaadvisors.com/advisory-firm-what-we-do/institutional-investors-capacity-development

Sheet Funds & LP Co-Investors
A1: Fund-level view: each row = one fund/vehicle with African pension/SWF involvement, all known LPs broken out.
A3: Fund / Vehicle | B3: Manager / GP | C3: Vintage | D3: Fund size (USD m) | E3: Asset class | F3: Geographic focus | G3: African PF/SWF LPs (count) | H3: Named African PF/SWF LPs | I3: DFI LPs (count) | J3: Named DFI LPs | K3: Other named LPs | L3: Co-investor pattern note
A4: Growth Investment Partners (GIP) Ghana | B4: BII-established platform | C4: 2023-launched, 2026 expansion | D4: ~70 (incl. Axis + Norfund 2026 round) | E4: Private credit / SME debt (local currency) | F4: Ghana | G4: 1 | H4: Axis Pension Trust (USD 5m, 2026) | I4: 2 | J4: BII (anchor), Norfund (USD 15m, 2026) | K4: — | L4: BII-anchored DFI + 1 Ghanaian pension trustee. First Ghanaian PF commitment under 5% alts rule.
A5: Growth Investment Partners (GIP) Zambia | B5: BII-established platform | C5: 2025 | D5: 70 | E5: Private credit / SME debt (local currency) | F5: Zambia | G5: 1 | H5: NAPSA Zambia (USD 17.5m) | I5: 2 | J5: BII (USD 37.5m anchor), Swedfund (USD 15m) | K5: — | L5: Largest single disclosed Zambian-pension alts commitment. Trilateral DFI+pension anchor model.
A6: Ci-Gaba Fund of Funds | B6: Savannah Impact Advisory | C6: 2026 | D6: 35 first close (target 91) | E6: FoF (PE/VC/Private credit) | F6: Ghana + Nigeria + Senegal + Côte d'Ivoire | G6: 2 + ~3 intermediated | H6: Axis Pension Trust, Enterprise Trustees, plus Stanbic IMS Ghana & CAL AM Ghana managing additional pension money | I6: 2 | J6: FSD Africa Investments (USD 7.5m), FMO | K6: Small Foundation | L6: West Africa's first domestically-domiciled private FoF. Ghanaian pensions >2/3 of first close.
A7: ARM-Harith Infrastructure Fund I | B7: ARM-Harith JV | C7: 2015 close | D7: ~30 | E7: Infrastructure | F7: Nigeria | G7: multiple (Nigerian PFAs) | H7: Stanbic IBTC Pension Managers, ARM Pension, other PFAs (named in industry coverage) | I7: 0 | J7: — | K7: — | L7: Landmark first-Nigerian-pension-funded infra fund.
A8: Oyass Capital | B8: SEAF (Small Enterprise Assistance Funds) | C8: 2024 | D8: ~82 (XOF 50bn) | E8: PE / SME | F8: Senegal | G8: 1 | H8: FONSIS | I8: 1 | J8: KfW (German cooperation) | K8: — | L8: FONSIS + KfW launch; SEAF mandate award after international tender.
A9: Yield Uganda Investment Fund | B9: Pearl Capital Partners | C9: 2017 | D9: ~22 (EUR 20m total commitments to date) | E9: PE / Agribusiness | F9: Uganda | G9: 1 | H9: NSSF Uganda (EUR 12m founding) | I9: 3 | J9: EU (via IFAD), Soros Economic Development Fund (OSF), FCA Investments | K9: — | L9: NSSF Uganda founding LP alongside EU + IFAD. [Phase 6 correction: NSSF Uganda's founding contribution was EUR 2m (not EUR 12m); EUR 12m was the TOTAL first close including EU/IFAD EUR 10m. Later EUR 8m added by Soros Economic Development Fund + FCA Investments brought total to EUR 20m.]
A10: Ascent Rift Valley Fund I (ARVF I) | B10: Ascent Capital Africa | C10: 2014–2015 | D10: 50 | E10: PE / SME growth | F10: Kenya, Uganda, Ethiopia | G10: 2 | H10: KPLC Pension Fund (USD 4m, 2014 — 'first East African pension LP in PE'), NMG Pension Fund (USD 1m, 2015 via STANLIB) | I10: 2 | J10: Norfund, OeEB (Austria) | K10: Family offices, other institutional investors | L10: Historical pioneer fund for East African pension PE participation.
A11: Ascent Rift Valley Fund II (ARVF II) | B11: Ascent Capital Africa | C11: 2018-2020 | D11: ~80-120 | E11: PE / SME growth | F11: Kenya, Uganda, Ethiopia, Rwanda, Tanzania | G11: 3 separate commitments | H11: KPLC Pension Fund x2 (likely main + Staff RBS), NMG Pension Fund | I11: 6 | J11: BII, BIO, FMO, IFC, Norfund, Proparco | K11: SDG Frontier Fund; PTA Zep-Re | L11: Strong DFI cluster alongside re-up of East African pension LPs. Source narrative: ARVF was 'the only local PE fund continually unlocking local pension investment' as of 2015.
A12: Adenia Capital V | B12: Adenia Partners | C12: 2024 | D12: 470 | E12: PE | F12: Pan-Africa | G12: >2 (named) + categorical | H12: PIC South Africa (named); Kenyan pension funds (cohort); Ghanaian pension funds (cohort) | I12: 10 | J12: FMO, Proparco, IFC, DEG, EIB, SIFEM, DFC, Norfund, FinDev Canada, Bpifrance (i.e., 10 DFIs per EIB disclosure) | K12: Blue Earth Capital, Casey Family Programs, South Suez Capital, European family offices | L12: ~30 LPs total; >60% historical DFI re-ups; categorical 'Kenyan + Ghanaian pension funds' mentioned in press release but not individually named. [Phase 6 update: comprehensive LP list confirmed via EIB disclosure. 10 DFIs + PIC SA + categorical Kenyan/Ghanaian PFs + family offices = ~30 LP entities total.]
A13: Catalyst Fund II | B13: Catalyst Principal Partners | C13: 2017 | D13: 155 | E13: PE | F13: Kenya, Uganda, Tanzania, Ethiopia, Zambia, Rwanda, DRC | G13: 1+ (cohort) | H13: 'Local pension funds' (NSSF Uganda likely; others not named) | I13: 5 | J13: BII (USD 30m), EIB, IFC, Proparco, Swedfund | K13: Family offices, regional investors | L13: Single largest East African PE fund with disclosed local-pension cohort.
A14: Helios Investors II/III/IV (historical) | B14: Helios Investment Partners | C14: 2009-2020 | D14: Multi-bn cumulative | E14: PE | F14: Pan-Africa | G14: 1 | H14: PIC South Africa (historical, recurring) | I14: multiple | J14: BII (since 2007), various DFIs | K14: Global pension funds, SWFs, endowments, family offices | L14: PIC has been recurring LP since Helios II; sizes not publicly disclosed.
A15: Vantage Mezzanine IV (Pan-African sub-fund) | B15: Vantage Capital | C15: 2021 | D15: ~350 target | E15: Private credit / Mezzanine | F15: Pan-Africa + Southern Africa | G15: multiple (cohort) | H15: 'A number of Southern African pension funds' (per Vantage disclosure; SA pension funds incl. BPOPF — see Phase 2 entry) | I15: 6 | J15: IFC, EIB, BII, Norfund, DEG, Finnfund | K15: European endowments, private-sector insurers | L15: Vantage's 'historical pattern' of substantial SA pension LP base; specific names not publicly itemised.
A16: Mediterrania Capital II / III / IV | B16: Mediterrania Capital Partners | C16: Various 2014-2024 | D16: EUR multi-100m | E16: PE | F16: North Africa + Sub-Saharan | G16: 1 | H16: CDG Morocco (historical LP) | I16: multiple | J16: CDP Group (Italy), EIB, AfDB, others (varying by vintage) | K16: European family offices | L16: Maghreb-focused; CDG Morocco historical LP.
A17: AfricInvest FIVE (Financial Inclusion Vehicle) | B17: AfricInvest | C17: Open-ended evergreen (started 2017) | D17: Multi-100m | E17: PE / Financial inclusion | F17: Africa | G17: 1 | H17: CBK Pension Fund Kenya (since Oct 2018 second close) | I17: 4 | J17: Norfund, IFU, AfDB (later), KfW (later) | K17: — | L17: Evergreen platform; CBK Pension Fund Kenya was first African pension LP in 2018; multiple closes since.
A18: Aleyo Capital Fund I | B18: Aleyo Capital | C18: 2017 | D18: ~43 | E18: PE / Domestic incubation | F18: Botswana + regional | G18: 1 | H18: BPOPF (anchor, BWP 500m / USD ~43m) | I18: 0 | J18: — | K18: — | L18: BPOPF domestic incubation programme — single-LP-anchor model.
A19: Africa Lighthouse Capital Fund I | B19: Africa Lighthouse Capital | C19: 2017 | D19: ~43 | E19: PE / Domestic + regional | F19: Botswana + regional | G19: 1 | H19: BPOPF (anchor, BWP 500m / USD ~43m) | I19: 0 | J19: — | K19: — | L19: Sister vehicle to Aleyo; BPOPF anchor.
A20: Africa50 (general) | B20: Africa50 (AfDB-affiliated) | C20: 2014-launched, ongoing | D20: 1,400+ AUM | E20: Infrastructure platform / direct co-invest | F20: Pan-Africa | G20: 1 (shareholder; PIC SA) | H20: PIC SA (USD 40m equity, April 2025); 31+ African government shareholders | I20: 2 | J20: AfDB (anchor sponsor), Bank Al-Maghrib, BCEAO | K20: — | L20: Continental infrastructure platform. PIC's 2025 commitment is largest single PF equity shareholding.
A21: Africa50 Infrastructure Acceleration Fund (IAF) | B21: Africa50 | C21: 2024 | D21: 222.5 first close (>275 mobilised) | E21: Infrastructure (PE-style) | F21: Pan-Africa | G21: 5+ named | H21: NSIA Nigeria, CDC Sénégal, CDC Benin, CNSS Togo, CDG Invest Morocco | I21: 2 | J21: AfDB, IFC | K21: Attijariwafa Bank (Morocco), Arab Bank for Economic Development in Africa, West African Development Bank (BOAD) | L21: First major pan-African infra fund MAJORITY-funded by African institutions. Africa50's flagship LP-style vehicle.
A22: Africa Finance Corporation (AFC) — equity shareholders | B22: AFC (multilateral) | C22: ongoing | D22: Multi-bn | E22: Infrastructure / institutional equity vehicle | F22: Pan-Africa | G22: 10+ African PF/SWF/sovereign shareholders | H22: PIC SA (USD 100m, 2022), Seychelles Pension Fund, Mauritius NPF + NSF, GIIF Ghana, CNPS Cameroon, CDC Gabon, Côte d'Ivoire, Sierra Leone, Egypt (2024), Rawbank DRC | I22: 0 (DFIs are not AFC shareholders; AFC IS itself a DFI) | J22: — | K22: Central Bank of Nigeria 38%; private investors 62% | L22: Continental institutional-equity vehicle. By count of institutions, AFC participation is the MOST COMMON form of cross-border African pension/SWF alts deployment.
A23: Pembani Remgro Infrastructure Fund | B23: Pembani Remgro Infrastructure Managers | C23: 2015 | D23: ~625 | E23: Infrastructure | F23: Pan-Africa | G23: 1 | H23: PIC South Africa (anchor, ~USD 250m) | I23: multiple | J23: Various DFIs and SA institutional investors | K23: — | L23: PIC anchor; significant African-LP-funded infra fund.
A24: Convergence Partners Communications Infrastructure Fund | B24: Convergence Partners | C24: Multiple vintages | D24: Multi-100m cumulative | E24: Infrastructure (digital/telecoms) | F24: Pan-Africa | G24: 1 | H24: PIC South Africa (historical) | I24: multiple | J24: Various DFIs | K24: — | L24: Digital infrastructure; PIC participant.
A25: Wessal Capital | B25: Wessal Capital partnership | C25: active | D25: USD 2.5bn target | E25: Direct (real estate / infra) | F25: Morocco | G25: 1 | H25: Ithmar Capital (Morocco SWF) | I25: 0 | J25: — | K25: Abu Dhabi, Kuwait, Qatar SWFs (Gulf SWF co-investors) | L25: Joint Morocco + Gulf SWF platform.
A26: Mohammed VI Fund for Investment | B26: Government of Morocco | C26: 2020 | D26: 4,500 capitalisation (MAD 45bn) | E26: SWF anchor — sectoral funds | F26: Morocco | G26: 1 | H26: Mohammed VI Fund itself (the allocator) | I26: 0 | J26: — | K26: Anchors various Moroccan sectoral funds | L26: Capitalised Moroccan strategic SWF — anchor for sub-funds.
A27: Nigeria Infrastructure Fund (NIF, NSIA sub-fund) | B27: NSIA Nigeria | C27: ongoing | D27: Multi-100m disclosed direct | E27: Direct / Infrastructure / Agribusiness / Healthcare | F27: Nigeria | G27: 1 | H27: NSIA (the SWF itself) | I27: multiple co-invest | J27: AfDB co-financing on selected deals; various | K27: — | L27: NIF is NSIA's direct-deal sub-fund; received USD 550m additional govt funding FY24.
A28: TSFE-ADQ Egyptian Health Platform | B28: TSFE + ADQ | C28: active | D28: USD ~2bn platform | E28: Direct / Healthcare | F28: Egypt | G28: 1 | H28: TSFE (the SWF itself) | I28: 0 | J28: — | K28: ADQ (UAE SWF) | L28: Bilateral SWF healthcare platform.
A29: Sahel Capital Fund for Agricultural Finance in Nigeria (FAFIN) | B29: Sahel Capital | C29: 2017 | D29: 65.9 | E29: PE / Agribusiness | F29: Nigeria | G29: 1 | H29: NSIA Nigeria | I29: 3 | J29: AfDB, BII, Dutch Good Growth Fund | K29: — | L29: NSIA's earliest disclosed PE fund LP position; alongside three DFIs.
A30: Capital Alliance Private Equity I-IV (CAPE) | B30: African Capital Alliance (ACA) | C30: 1998-ongoing | D30: >1,000 cumulative | E30: PE | F30: Nigeria + West Africa | G30: historical cohort | H30: Nigerian PFAs (categorical historical disclosure; ACA explicitly 'championed PE inclusion as allowable Nigerian pension asset class') | I30: multiple | J30: BII (CAPE IV); various DFIs across vintages | K30: — | L30: First Nigerian PE firm (founded 1997); CAPE I was Nigeria's first PE fund (1998). Continental pioneer of pension-PE inclusion.
A31: Rwanda SME Growth Fund | B31: Enko Capital (Rwanda subsidiary) | C31: 2026 | D31: 30 first close (target 100) | E31: PE / SME growth (local-currency) | F31: Rwanda | G31: 1 | H31: RSSB (Rwanda Social Security Board) — USD 30m anchor + USD 3m TA seed | I31: 1 | J31: FSD Africa Investments (structuring + planned guarantee) | K31: — | L31: First permanent capital vehicle anchored by an African pension fund (per RSSB CEO). Three regional firsts: pension-fund-led SME-only mandate, anchor permanent-capital vehicle, pension-fund TA facility.
A32: Mirepa Capital SME Fund I | B32: Mirepa Investment Advisors | C32: 2023 | D32: ~10-12 (GHS 120m initial close) | E32: PE / SME growth | F32: Ghana | G32: 2 named pension trustees + categorical CAMCOL schemes | H32: Petra Trust; Axis Pensions; multiple schemes via CAL Asset Management Company (CAMCOL); Venture Capital Trust Fund (VCTF) | I32: 0 | J32: — | K32: VCTF is a Ghanaian quasi-government VC fund (not strictly a DFI) | L32: Second Ghana fund anchored solely by local investors (after Injaro IGVCF). 100% local-LP-funded. Confirms Ghana's emerging mandated-minimum-alts policy is producing real deal flow.
A33: Injaro Ghana Venture Capital Fund (IGVCF) | B33: Injaro Investment Advisors | C33: 2023 | D33: ~17.4 (GHS 216m final close Dec 2023) | E33: PE / SME / VC | F33: Ghana + Côte d'Ivoire | G33: multiple Ghanaian pension funds (anchor cohort) | H33: Specific names not individually disclosed | I33: 0 | J33: — | K33: Venture Capital Trust Fund (VCTF) of Ghana | L33: FIRST Ghana fund of its kind anchored by local pension funds. Historical precedent for Mirepa I, Ci-Gaba, GIP Ghana model. Ghana cedi-denominated.
A34: Africa Food Security Fund (AFSF) | B34: Zebu Investment Partners | C34: 2019 | D34: 84 | E34: PE / agriculture / food security | F34: Sub-Saharan Africa | G34: 1 | H34: PIC on behalf of GEPF (South Africa) | I34: 5 | J34: AfDB; BII (CDC Group); Dutch Good Growth Fund (DGGF); IFU; EBID | K34: Kuramo Capital Management | L34: DGGF news release names PIC/GEPF in first-round investor group alongside DFIs and DGGF; Kuramo subsequently joined to bring commitments to USD 84m.

Sheet DFI Co-Investor Patterns
A1: DFI co-investor frequency: refreshed after May 2026 inclusion audit; counts only retained vehicles with African PF/SWF involvement.
A3: DFI / Catalytic capital provider | B3: Co-investments in funds with African PF/SWF LP | C3: Notable vehicles | D3: Strategic role | E3: Frequency tier
A4: BII | B4: 9 | C4: Ascent Rift Valley Fund II (ARVF II); Capital Alliance Private Equity I-IV (CAPE); Catalyst Fund II; Growth Investment Partners (GIP) Ghana; Growth Investment Partners (GIP) Zambia; Helios Investors II/III/IV (historical); Sahel Capital Fund for Agricultural Finance in Nigeria (FAFIN); Vantage Mezzanine IV (Pan-African sub-fund); Africa Food Security Fund (AFSF) | D4: Frequent anchor/catalytic DFI, including BII-established GIP platforms designed to crowd in local pension capital. | E4: 1 (Top tier)
A5: AfDB | B5: 7 | C5: AfricInvest FIVE (Financial Inclusion Vehicle); Africa50 (general); Africa50 Infrastructure Acceleration Fund (IAF); Mediterrania Capital II / III / IV; Nigeria Infrastructure Fund (NIF, NSIA sub-fund); Sahel Capital Fund for Agricultural Finance in Nigeria (FAFIN); Africa Food Security Fund (AFSF) | D5: Co-investor or catalytic-capital provider appearing in retained vehicles with African PF/SWF participation. | E5: 1 (Top tier)
A6: Norfund | B6: 6 | C6: Adenia Capital V; AfricInvest FIVE (Financial Inclusion Vehicle); Ascent Rift Valley Fund I (ARVF I); Ascent Rift Valley Fund II (ARVF II); Growth Investment Partners (GIP) Ghana; Vantage Mezzanine IV (Pan-African sub-fund) | D6: Frequent DFI co-investor in SME, infrastructure, and financial inclusion vehicles. | E6: 1 (Top tier)
A7: IFC | B7: 5 | C7: Adenia Capital V; Africa50 Infrastructure Acceleration Fund (IAF); Ascent Rift Valley Fund II (ARVF II); Catalyst Fund II; Vantage Mezzanine IV (Pan-African sub-fund) | D7: World Bank Group investor and disclosure source; active in flagship PE/infrastructure vehicles. | E7: 2 (Active)
A8: EIB | B8: 4 | C8: Adenia Capital V; Catalyst Fund II; Mediterrania Capital II / III / IV; Vantage Mezzanine IV (Pan-African sub-fund) | D8: Co-investor or catalytic-capital provider appearing in retained vehicles with African PF/SWF participation. | E8: 2 (Active)
A9: FMO | B9: 3 | C9: Adenia Capital V; Ascent Rift Valley Fund II (ARVF II); Ci-Gaba Fund of Funds | D9: Frequent co-investor across funds and fund-of-funds with African pension/SWF participation. | E9: 2 (Active)
A10: Proparco | B10: 3 | C10: Adenia Capital V; Ascent Rift Valley Fund II (ARVF II); Catalyst Fund II | D10: Co-investor or catalytic-capital provider appearing in retained vehicles with African PF/SWF participation. | E10: 2 (Active)
A11: DEG | B11: 2 | C11: Adenia Capital V; Vantage Mezzanine IV (Pan-African sub-fund) | D11: Co-investor or catalytic-capital provider appearing in retained vehicles with African PF/SWF participation. | E11: 3 (Selective / TA)
A12: FSD Africa Investments | B12: 2 | C12: Ci-Gaba Fund of Funds; Rwanda SME Growth Fund | D12: Catalytic capital provider focused on local institutional-capital mobilization and product design. | E12: 3 (Selective / TA)
A13: KfW | B13: 2 | C13: AfricInvest FIVE (Financial Inclusion Vehicle); Oyass Capital | D13: Co-investor or catalytic-capital provider appearing in retained vehicles with African PF/SWF participation. | E13: 3 (Selective / TA)
A14: MiDA Advisors | B14: 2 | C14: AOFSA pooled infrastructure mandates (South Africa); KEPFIC pooled mandates (Kenya) | D14: Technical-assistance and transaction-advisory provider for pension-consortium infrastructure pipelines. | E14: 3 (Selective / TA)
A15: Swedfund | B15: 2 | C15: Catalyst Fund II; Growth Investment Partners (GIP) Zambia | D15: Co-investor or catalytic-capital provider appearing in retained vehicles with African PF/SWF participation. | E15: 3 (Selective / TA)
... A50: Kuramo Capital Management | B50: 1 | C50: Africa Food Security Fund (AFSF) | D50: Other named LP / fund-of-funds investor appearing in retained vehicles with African PF/SWF participation. | E50: 3 (Selective / TA)

Sheet Country Summary
A1: Country coverage summary — counts and AUM aggregated from preceding sheets
A3: Country | B3: # SWFs (>$0 AUM) | C3: # Pension funds listed | D3: Total SWF AUM (USD m) | E3: Total Pension AUM (USD m) | F3: Combined (USD m)
A4: Algeria | B4: =COUNTIFS('Sovereign Wealth Funds'!A:A,A4,'Sovereign Wealth Funds'!E:E,">0") | C4: =COUNTIF('Pension Funds'!A:A,A4) | D4: =SUMIF('Sovereign Wealth Funds'!A:A,A4,'Sovereign Wealth Funds'!E:E) | E4: =SUMIF('Pension Funds'!A:A,A4,'Pension Funds'!E:E) | F4: =D4+E4
A5: Angola | B5: =COUNTIFS('Sovereign Wealth Funds'!A:A,A5,'Sovereign Wealth Funds'!E:E,">0") | C5: =COUNTIF('Pension Funds'!A:A,A5) | D5: =SUMIF('Sovereign Wealth Funds'!A:A,A5,'Sovereign Wealth Funds'!E:E) | E5: =SUMIF('Pension Funds'!A:A,A5,'Pension Funds'!E:E) | F5: =D5+E5
A6: Benin | B6: =COUNTIFS('Sovereign Wealth Funds'!A:A,A6,'Sovereign Wealth Funds'!E:E,">0") | C6: =COUNTIF('Pension Funds'!A:A,A6) | D6: =SUMIF('Sovereign Wealth Funds'!A:A,A6,'Sovereign Wealth Funds'!E:E) | E6: =SUMIF('Pension Funds'!A:A,A6,'Pension Funds'!E:E) | F6: =D6+E6
A7: Botswana | B7: =COUNTIFS('Sovereign Wealth Funds'!A:A,A7,'Sovereign Wealth Funds'!E:E,">0") | C7: =COUNTIF('Pension Funds'!A:A,A7) | D7: =SUMIF('Sovereign Wealth Funds'!A:A,A7,'Sovereign Wealth Funds'!E:E) | E7: =SUMIF('Pension Funds'!A:A,A7,'Pension Funds'!E:E) | F7: =D7+E7
A8: Burkina Faso | B8: =COUNTIFS('Sovereign Wealth Funds'!A:A,A8,'Sovereign Wealth Funds'!E:E,">0") | C8: =COUNTIF('Pension Funds'!A:A,A8) | D8: =SUMIF('Sovereign Wealth Funds'!A:A,A8,'Sovereign Wealth Funds'!E:E) | E8: =SUMIF('Pension Funds'!A:A,A8,'Pension Funds'!E:E) | F8: =D8+E8
A9: Burundi | B9: =COUNTIFS('Sovereign Wealth Funds'!A:A,A9,'Sovereign Wealth Funds'!E:E,">0") | C9: =COUNTIF('Pension Funds'!A:A,A9) | D9: =SUMIF('Sovereign Wealth Funds'!A:A,A9,'Sovereign Wealth Funds'!E:E) | E9: =SUMIF('Pension Funds'!A:A,A9,'Pension Funds'!E:E) | F9: =D9+E9
A10: Cabo Verde | B10: =COUNTIFS('Sovereign Wealth Funds'!A:A,A10,'Sovereign Wealth Funds'!E:E,">0") | C10: =COUNTIF('Pension Funds'!A:A,A10) | D10: =SUMIF('Sovereign Wealth Funds'!A:A,A10,'Sovereign Wealth Funds'!E:E) | E10: =SUMIF('Pension Funds'!A:A,A10,'Pension Funds'!E:E) | F10: =D10+E10
A11: Cameroon | B11: =COUNTIFS('Sovereign Wealth Funds'!A:A,A11,'Sovereign Wealth Funds'!E:E,">0") | C11: =COUNTIF('Pension Funds'!A:A,A11) | D11: =SUMIF('Sovereign Wealth Funds'!A:A,A11,'Sovereign Wealth Funds'!E:E) | E11: =SUMIF('Pension Funds'!A:A,A11,'Pension Funds'!E:E) | F11: =D11+E11
A12: Central African Republic | B12: =COUNTIFS('Sovereign Wealth Funds'!A:A,A12,'Sovereign Wealth Funds'!E:E,">0") | C12: =COUNTIF('Pension Funds'!A:A,A12) | D12: =SUMIF('Sovereign Wealth Funds'!A:A,A12,'Sovereign Wealth Funds'!E:E) | E12: =SUMIF('Pension Funds'!A:A,A12,'Pension Funds'!E:E) | F12: =D12+E12
A13: Chad | B13: =COUNTIFS('Sovereign Wealth Funds'!A:A,A13,'Sovereign Wealth Funds'!E:E,">0") | C13: =COUNTIF('Pension Funds'!A:A,A13) | D13: =SUMIF('Sovereign Wealth Funds'!A:A,A13,'Sovereign Wealth Funds'!E:E) | E13: =SUMIF('Pension Funds'!A:A,A13,'Pension Funds'!E:E) | F13: =D13+E13
A14: Comoros | B14: =COUNTIFS('Sovereign Wealth Funds'!A:A,A14,'Sovereign Wealth Funds'!E:E,">0") | C14: =COUNTIF('Pension Funds'!A:A,A14) | D14: =SUMIF('Sovereign Wealth Funds'!A:A,A14,'Sovereign Wealth Funds'!E:E) | E14: =SUMIF('Pension Funds'!A:A,A14,'Pension Funds'!E:E) | F14: =D14+E14
A15: Congo (Brazzaville) | B15: =COUNTIFS('Sovereign Wealth Funds'!A:A,A15,'Sovereign Wealth Funds'!E:E,">0") | C15: =COUNTIF('Pension Funds'!A:A,A15) | D15: =SUMIF('Sovereign Wealth Funds'!A:A,A15,'Sovereign Wealth Funds'!E:E) | E15: =SUMIF('Pension Funds'!A:A,A15,'Pension Funds'!E:E) | F15: =D15+E15
... A57: Zimbabwe | B57: =COUNTIFS('Sovereign Wealth Funds'!A:A,A57,'Sovereign Wealth Funds'!E:E,">0") | C57: =COUNTIF('Pension Funds'!A:A,A57) | D57: =SUMIF('Sovereign Wealth Funds'!A:A,A57,'Sovereign Wealth Funds'!E:E) | E57: =SUMIF('Pension Funds'!A:A,A57,'Pension Funds'!E:E) | F57: =D57+E57
A58: TOTAL | B58: =SUM(B4:B57) | C58: =SUM(C4:C57) | D58: =SUM(D4:D57) | E58: =SUM(E4:E57) | F58: =SUM(F4:F57)

Sheet Methodology & Caveats
A1: Methodology, sources, and important caveats
A3: Scope | B3: All 54 African countries. Allocator universe: sovereign wealth funds (any mandate type) plus pension funds of any kind (public, private, multi-employer, umbrella). Real estate is excluded per scoping; alts of interest are PE/VC, private credit & infrastructure, and direct/co-investments.
A5: AUM figures | B5: All AUM values are USD-converted approximations and should be treated as order-of-magnitude only. Currency basis (local) and as-of year are noted. Where the institution reports in a local currency, the USD value will move with FX as much as with portfolio performance. Confidence flags reflect source quality, not portfolio performance.
A7: Confidence flags | B7: H = High: AUM published in audited annual report or regulator return within last 18 months. M = Medium: AUM from secondary databases, trade press, or older primary disclosure. L = Low: AUM is estimated, dated, or based on indirect inference (e.g., regulatory share of contributions). Low-confidence rows MUST be verified before academic publication.
A9: Universe completeness | B9: Sovereign wealth funds: substantively complete (Africa has ~22 operational SWFs plus several proposed/planned). Pension funds: covers the largest scheme(s) per country plus the full PFA universe for Nigeria and the major schemes for South Africa, Morocco, and Kenya. Smaller occupational schemes (especially South Africa's ~1,400 registered schemes, Kenya's ~1,300, and Mauritius's standalone corporate schemes) are NOT individually listed — most are too small to make alts commitments. Aggregate AUM for these unlisted schemes is material in SA and Kenya and should be referenced via FSCA and RBA aggregate reports.
A11: Source priorities for verification | B11: Phase-2 verification should pull, in this order: (1) audited annual reports from each institution's website; (2) regulator returns (FSCA Reg 28, PenCom Q-reports, RBA industry reports, NPRA Ghana, CIPRES bulletins, ACAPS Morocco); (3) SWF databases (SWFI, Global SWF, IFSWF); (4) AVCA/SAVCA/EAVCA LP surveys; (5) trade press (African Private Equity News, Africa Capital Digest, *DealStreetAfrica*). Where access is available: Preqin and PitchBook LP profiles. Document the source URL + access date for each AUM figure before publication.
A13: Known limitations | B13: 1) Several Francophone CIPRES funds and most North African public PFs do not publish portfolio-detail in English; verify via local-language sources. 2) Ethiopian Investment Holdings AUM is the book value of SOE stakes, not investable capital — apples-to-oranges with cash-funded SWFs. 3) South African umbrella DC funds (Sanlam Umbrella, Old Mutual SuperFund, Alexforbes) are intermediaries — alts commitments flow through underlying portfolio managers, not from the umbrella entity directly. 4) Several proposed SWFs (Kenya, Tanzania) and dormant SWFs (Zimbabwe SWFZ) are included for completeness but have no investable capital. 5) Libya's LIA is mostly under UN sanctions; pre-2011 alts holdings are partially documented but unlikely to be acted on currently.
A15: Look-through note (CRITICAL) | B15: Many of the largest African pension pools (notably GEPF in South Africa and the Moroccan parastatal schemes managed by CDG) deploy alts via intermediary asset managers. When attributing alts commitments to allocators, the methodology choice is: (a) attribute to ultimate asset owner (e.g., 'GEPF committed via PIC to Helios IV'), or (b) attribute to the intermediary manager. Default rule for this research is (a) — ultimate asset owner — with the intermediary documented in the same row. This avoids double-counting and is more useful for the academic question of which institutions are deploying capital.
A17: Next phase | B17: Phase 2 (evidence layer) takes this roster, drops below USD 500m, and pursues for each remaining institution: (i) most recent annual report; (ii) regulator filing for the most recent reporting period; (iii) news search for LP mentions in African PE/infra fund closes over the past 7 years; (iv) GP-side disclosure: for each of the ~30 most active African-focused GPs, harvest every disclosed LP mention since 2018.
A19: Commitments Database scope (clarified)
A20: The Commitments Database contains ONLY African pension fund and sovereign wealth fund allocator-to-fund-or-deal commitments. It also includes adjacent entities that are functionally allocator-like and integral to the SWF/pension narrative: (i) sovereign governments making direct AFC equity investments (Côte d'Ivoire, Sierra Leone, Egypt) — functionally similar to SWF deployment; (ii) the KEPFIC pension-fund consortium; (iii) categorical 'multiple Nigerian PFAs' / 'Kenyan pension funds' / 'Ghanaian pension funds' cohort entries where the source explicitly identifies pension fund participation but doesn't name individual schemes. DFI catalytic capital providers (FSDAi, Soros Economic Development Fund, FCA Investments, etc.), asset managers acting as intermediaries (Old Mutual IG, Ninety One, Stanbic IMS Ghana, CAL Asset Management Ghana), and commercial banks (Rawbank, Attijariwafa, NIB Egypt) are NOT in the Commitments Database — they appear in the 'Funds & LP Co-Investors' tab as fund-level co-LPs, and in the 'DFI Co-Investor Patterns' tab for frequency analysis.
A22: 2026-05-14 inclusion audit | B22: Rows now require evidence of actual African PF/SWF participation for the fund/vehicle. DFI-only, planned, expected, targeted, generic LP-base, and MoU-only rows were removed from the fund and commitment fact tables. KEPFIC and AOFSA are retained only as aggregate pooled-mandate archetypes because public sources evidence actual member-fund investments/commitments; individual member-only rows were removed from the Commitments Database. See Inclusion Audit tab.
A23: Pipeline & Mandates category | B23: Targeted/expected/planned rows are separated into the Pipeline & Mandates tab and excluded from the Commitments Database until actual allocator-to-vehicle commitments are publicly evidenced.
A24: DFI canonicalization | B24: DFI nomenclature is canonicalized for the web app network graph: each DFI has one node even when source text uses variants such as BII/CDC, CDC Group/BII, EIB Global, Findev Canada, FSDAi, or Proparco/FISEA.

Sheet Inclusion Audit
A1: Sheet | B1: Original row | C1: Vehicle / entity | D1: Column H / named African PF/SWF evidence | E1: Decision | F1: Audit confidence | G1: Rationale | H1: Source URLs
A2: Funds & LP Co-Investors | B2: 4 | C2: Growth Investment Partners (GIP) Ghana | D2: Axis Pension Trust (USD 5m, 2026) | E2: Include | F2: Include | G2: Column H identifies a named African PF/SWF, a named cohort, or the allocator itself is an African SWF/PF vehicle.
A3: Funds & LP Co-Investors | B3: 5 | C3: Growth Investment Partners (GIP) Zambia | D3: NAPSA Zambia (USD 17.5m) | E3: Include | F3: Include | G3: Column H identifies a named African PF/SWF, a named cohort, or the allocator itself is an African SWF/PF vehicle.
A4: Funds & LP Co-Investors | B4: 6 | C4: Ci-Gaba Fund of Funds | D4: Axis Pension Trust, Enterprise Trustees, plus Stanbic IMS Ghana & CAL AM Ghana managing additional pension money | E4: Include | F4: Include | G4: Column H identifies a named African PF/SWF, a named cohort, or the allocator itself is an African SWF/PF vehicle.
A5: Funds & LP Co-Investors | B5: 7 | C5: ARM-Harith Infrastructure Fund I | D5: Stanbic IBTC Pension Managers, ARM Pension, other PFAs (named in industry coverage) | E5: Include | F5: Include | G5: Column H identifies a named African PF/SWF, a named cohort, or the allocator itself is an African SWF/PF vehicle.
A6: Funds & LP Co-Investors | B6: 8 | C6: ARM-Harith Climate & Transition Infrastructure Fund (ACT Fund) | D6: Nigerian PFAs (expected; 75% local-currency tranche designed to unlock them) | E6: Exclude | F6: Excluded - insufficient actual African PF/SWF evidence | G6: Pipeline/catalytic structure only. Public evidence says FSDAi commitment is expected to unlock Nigerian pension contributions; no named/closed PFA LP evidence found. | H6: https://archive.fsdafrica.org/arm-harith-and-fsd-africa-investments-announce-gbp-10m-commitment-to-unlock-nigerian-pension-funds-and-catalyse-local-capital-for-infrastructure/
A7: Funds & LP Co-Investors | B7: 9 | C7: Oyass Capital | D7: FONSIS | E7: Include | F7: Include | G7: Column H identifies a named African PF/SWF, a named cohort, or the allocator itself is an African SWF/PF vehicle.
A8: Funds & LP Co-Investors | B8: 10 | C8: Yield Uganda Investment Fund | D8: NSSF Uganda (EUR 12m founding) | E8: Include | F8: Include | G8: Column H identifies a named African PF/SWF, a named cohort, or the allocator itself is an African SWF/PF vehicle.
A9: Funds & LP Co-Investors | B9: 11 | C9: Ascent Rift Valley Fund I (ARVF I) | D9: KPLC Pension Fund (USD 4m, 2014 — 'first East African pension LP in PE'), NMG Pension Fund (USD 1m, 2015 via STANLIB) | E9: Include | F9: Include | G9: Column H identifies a named African PF/SWF, a named cohort, or the allocator itself is an African SWF/PF vehicle.
A10: Funds & LP Co-Investors | B10: 12 | C10: Ascent Rift Valley Fund II (ARVF II) | D10: KPLC Pension Fund x2 (likely main + Staff RBS), NMG Pension Fund | E10: Include | F10: Include | G10: Column H identifies a named African PF/SWF, a named cohort, or the allocator itself is an African SWF/PF vehicle.
A11: Funds & LP Co-Investors | B11: 13 | C11: Adenia Capital V | D11: PIC South Africa (named); Kenyan pension funds (cohort); Ghanaian pension funds (cohort) | E11: Include | F11: Include | G11: Column H identifies a named African PF/SWF, a named cohort, or the allocator itself is an African SWF/PF vehicle. | H11: https://impactalpha.com/african-pension-funds-back-adenia-capitals-fifth-impact-private-equity-fund/ ; https://www.adenia.com/investments/
A12: Funds & LP Co-Investors | B12: 14 | C12: Adenia Africa Entrepreneurial Fund (AEF) | D12: Not individually named | E12: Exclude | F12: Excluded - insufficient actual African PF/SWF evidence | G12: No public African PF/SWF LP identified for AEF; available DFI disclosures name Proparco/BIO/AfDB-style support rather than African pension/SWF LPs.
A13: Funds & LP Co-Investors | B13: 15 | C13: Catalyst Fund II | D13: 'Local pension funds' (NSSF Uganda likely; others not named) | E13: Include | F13: Include | G13: Column H identifies a named African PF/SWF, a named cohort, or the allocator itself is an African SWF/PF vehicle.
A14: Funds & LP Co-Investors | B14: 16 | C14: Helios Investors II/III/IV (historical) | D14: PIC South Africa (historical, recurring) | E14: Include | F14: Include | G14: Column H identifies a named African PF/SWF, a named cohort, or the allocator itself is an African SWF/PF vehicle.
A15: Funds & LP Co-Investors | B15: 17 | C15: Helios CLEAR Fund (Climate, Energy Access & Resilience) | D15: None publicly named (Helios indicates SWFs + pension funds among LPs but unspecified) | E15: Exclude | F15: Excluded - insufficient actual African PF/SWF evidence | G15: First-close evidence names DFIs/impact investors; no African PF/SWF LP publicly named. Generic Helios pension/SWF investor-base language is not fund-specific enough.
A16: Funds & LP Co-Investors | B16: 18 | C16: Helios Fund V | D16: Not yet disclosed publicly | E16: Exclude | F16: Excluded - insufficient actual African PF/SWF evidence | G16: Newer fundraising row with no disclosed African PF/SWF LP.
A17: Funds & LP Co-Investors | B17: 19 | C17: DPI African Development Partners IV (ADP IV) | D17: Not yet disclosed publicly (DPI LP base described as including 'sovereign wealth funds + public pension funds' generally) | E17: Exclude | F17: Excluded - insufficient actual African PF/SWF evidence | G17: Generic global LP-base language only; no African PF/SWF commitment publicly named for ADP IV.
A18: Funds & LP Co-Investors | B18: 20 | C18: Phatisa Food Fund 3 | D18: Not publicly named | E18: Exclude | F18: Excluded - insufficient actual African PF/SWF evidence | G18: First-close release names BII, FinDev Canada, Norfund, Swedfund, IFC and Phatisa; no African PF/SWF LP. | H18: https://www.phatisa.com/post/phatisa-food-fund-3-reaches-us-86-million-first-close-and-signs-its-first-investment
A19: Funds & LP Co-Investors | B19: 21 | C19: Vantage Mezzanine IV (Pan-African sub-fund) | D19: 'A number of Southern African pension funds' (per Vantage disclosure; SA pension funds incl. BPOPF — see Phase 2 entry) | E19: Include | F19: Include | G19: Column H identifies a named African PF/SWF, a named cohort, or the allocator itself is an African SWF/PF vehicle.
A20: Funds & LP Co-Investors | B20: 22 | C20: Mediterrania Capital II / III / IV | D20: CDG Morocco (historical LP) | E20: Include | F20: Include | G20: Column H identifies a named African PF/SWF, a named cohort, or the allocator itself is an African SWF/PF vehicle.
A21: Funds & LP Co-Investors | B21: 23 | C21: BluePeak Private Capital Fund II | D21: Not publicly named | E21: Exclude | F21: Excluded - insufficient actual African PF/SWF evidence | G21: First-close releases identify European DFIs only: BII, FMO, Swedfund and SIFEM; no African PF/SWF LP. | H21: https://sifem.ch/sifem-invests-in-bluepeak-fund-ii/ ; https://www.fmo.nl/news-detail/6cae1491-d8e7-4b1e-924a-fd5f01b4bd08/european-dfis-invest-in-bluepeak-private-capital-fund-ii-to-boost-jobs-resilience-and-private-sector-growth
A22: Funds & LP Co-Investors | B22: 24 | C22: East Africa Growth Holdings (EAGH) | D22: Not publicly named | E22: Exclude | F22: Excluded - insufficient actual African PF/SWF evidence | G22: Vehicle evidence identifies AfricInvest/FMO/Norfund and I&M transaction context, not an African PF/SWF LP.
A23: Funds & LP Co-Investors | B23: 25 | C23: AfricInvest FIVE (Financial Inclusion Vehicle) | D23: CBK Pension Fund Kenya (since Oct 2018 second close) | E23: Include | F23: Include | G23: Column H identifies a named African PF/SWF, a named cohort, or the allocator itself is an African SWF/PF vehicle.
A24: Funds & LP Co-Investors | B24: 26 | C24: Aleyo Capital Fund I | D24: BPOPF (anchor, BWP 500m / USD ~43m) | E24: Include | F24: Include | G24: Column H identifies a named African PF/SWF, a named cohort, or the allocator itself is an African SWF/PF vehicle.
A25: Funds & LP Co-Investors | B25: 27 | C25: Africa Lighthouse Capital Fund I | D25: BPOPF (anchor, BWP 500m / USD ~43m) | E25: Include | F25: Include | G25: Column H identifies a named African PF/SWF, a named cohort, or the allocator itself is an African SWF/PF vehicle.
A26: Funds & LP Co-Investors | B26: 28 | C26: Africa50 (general) | D26: PIC SA (USD 40m equity, April 2025); 31+ African government shareholders | E26: Include | F26: Include | G26: Column H identifies a named African PF/SWF, a named cohort, or the allocator itself is an African SWF/PF vehicle.
A27: Funds & LP Co-Investors | B27: 29 | C27: Africa50 Infrastructure Acceleration Fund (IAF) | D27: NSIA Nigeria, CDC Sénégal, CDC Benin, CNSS Togo, CDG Invest Morocco | E27: Include | F27: Include | G27: Column H identifies a named African PF/SWF, a named cohort, or the allocator itself is an African SWF/PF vehicle.
A28: Funds & LP Co-Investors | B28: 30 | C28: Africa Finance Corporation (AFC) — equity shareholders | D28: PIC SA (USD 100m, 2022), Seychelles Pension Fund, Mauritius NPF + NSF, GIIF Ghana, CNPS Cameroon, CDC Gabon, Côte d'Ivoire, Sierra Leone, Egypt (2024), Rawbank DRC | E28: Include | F28: Include | G28: Column H identifies a named African PF/SWF, a named cohort, or the allocator itself is an African SWF/PF vehicle.
A29: Funds & LP Co-Investors | B29: 31 | C29: Pembani Remgro Infrastructure Fund | D29: PIC South Africa (anchor, ~USD 250m) | E29: Include | F29: Include | G29: Column H identifies a named African PF/SWF, a named cohort, or the allocator itself is an African SWF/PF vehicle.
A30: Funds & LP Co-Investors | B30: 32 | C30: Convergence Partners Communications Infrastructure Fund | D30: PIC South Africa (historical) | E30: Include | F30: Include | G30: Column H identifies a named African PF/SWF, a named cohort, or the allocator itself is an African SWF/PF vehicle.
A31: Funds & LP Co-Investors | B31: 33 | C31: Wessal Capital | D31: Ithmar Capital (Morocco SWF) | E31: Include | F31: Include | G31: Column H identifies a named African PF/SWF, a named cohort, or the allocator itself is an African SWF/PF vehicle.
A32: Funds & LP Co-Investors | B32: 34 | C32: Mohammed VI Fund for Investment | D32: Mohammed VI Fund itself (the allocator) | E32: Include | F32: Include | G32: Column H identifies a named African PF/SWF, a named cohort, or the allocator itself is an African SWF/PF vehicle.
A33: Funds & LP Co-Investors | B33: 35 | C33: Nigeria Infrastructure Fund (NIF, NSIA sub-fund) | D33: NSIA (the SWF itself) | E33: Include | F33: Include | G33: Column H identifies a named African PF/SWF, a named cohort, or the allocator itself is an African SWF/PF vehicle.
A34: Funds & LP Co-Investors | B34: 36 | C34: TSFE-ADQ Egyptian Health Platform | D34: TSFE (the SWF itself) | E34: Include | F34: Include | G34: Column H identifies a named African PF/SWF, a named cohort, or the allocator itself is an African SWF/PF vehicle.
A35: Funds & LP Co-Investors | B35: 37 | C35: KEPFIC pooled mandates (Kenya) | D35: 24 Kenyan retirement benefit funds (named on KEPFIC site); collective ~1/3 of total Kenyan pension AUM | E35: Move to Pipeline & Mandates | F35: Moved - aggregate pooled mandate | G35: Aggregate pooled mandate / consortium archetype, not a conventional fund vehicle LP row. Kept out of Fund Vehicles and Commitments Database to avoid treating a mandate platform as a fund commitment. | H35: https://www.ifc.org/en/stories/2023/pooling-pensions-in-kenya ; https://www.midaadvisors.com/advisory-firm-financing-the-development-of-critical-infrastructure-in-kenya-with-local-institutional-capital
A36: Funds & LP Co-Investors | B36: 38 | C36: Sahel Capital Fund for Agricultural Finance in Nigeria (FAFIN) | D36: NSIA Nigeria | E36: Include | F36: Include | G36: Column H identifies a named African PF/SWF, a named cohort, or the allocator itself is an African SWF/PF vehicle.
A37: Funds & LP Co-Investors | B37: 39 | C37: Sahel Agribusiness Private Debt Fund | D37: Targets Nigerian PFAs + insurers as core LPs; not individually disclosed | E37: Exclude | F37: Excluded - insufficient actual African PF/SWF evidence | G37: Launch evidence says subscription is open to/targeting qualified institutional investors including pension funds; no actual PFA allocation disclosed. | H37: https://www.ecofinagency.com/news-finances/2502-53253-nigerian-investment-firm-sahel-capital-launches-55-million-fund-to-narrow-farm-finance-gap
A38: Funds & LP Co-Investors | B38: 40 | C38: Capital Alliance Private Equity I-IV (CAPE) | D38: Nigerian PFAs (categorical historical disclosure; ACA explicitly 'championed PE inclusion as allowable Nigerian pension asset class') | E38: Include | F38: Include | G38: Column H identifies a named African PF/SWF, a named cohort, or the allocator itself is an African SWF/PF vehicle.
A39: Funds & LP Co-Investors | B39: 41 | C39: Adenia Africa Entrepreneurial Fund (AEF) | D39: Not individually named; possibly some Kenyan/Ghanaian PF cohort | E39: Exclude | F39: Excluded - insufficient actual African PF/SWF evidence | G39: No public African PF/SWF LP identified for AEF; available DFI disclosures name Proparco/BIO/AfDB-style support rather than African pension/SWF LPs.
A40: Funds & LP Co-Investors | B40: 42 | C40: Rwanda SME Growth Fund | D40: RSSB (Rwanda Social Security Board) — USD 30m anchor + USD 3m TA seed | E40: Include | F40: Include | G40: Column H identifies a named African PF/SWF, a named cohort, or the allocator itself is an African SWF/PF vehicle.
A41: Funds & LP Co-Investors | B41: 43 | C41: AOFSA pooled infrastructure mandates (South Africa) | D41: GEPF; EPPF; Telkom Retirement Fund; Transnet Retirement Fund; National Fund for Municipal Workers; KZN Joint Municipal Pension Fund (NJMPF); KZN Municipal Pension Fund; Motor Industry Retirement Fund (named); 4-7 additional founding members not individually named | E41: Move to Pipeline & Mandates | F41: Moved - aggregate pooled mandate | G41: Aggregate pooled mandate / consortium archetype, not a conventional fund vehicle LP row. Kept out of Fund Vehicles and Commitments Database to avoid treating a mandate platform as a fund commitment. | H41: https://www.engineeringnews.co.za/article/aofsa-exceeds-infrastructure-investment-target-as-it-marks-first-anniversary-2022-11-21 ; https://www.midaadvisors.com/advisory-firm-what-we-do/institutional-investors-capacity-development
A42: Funds & LP Co-Investors | B42: 44 | C42: Mirepa Capital SME Fund I | D42: Petra Trust; Axis Pensions; multiple schemes via CAL Asset Management Company (CAMCOL); Venture Capital Trust Fund (VCTF) | E42: Include | F42: Include | G42: Column H identifies a named African PF/SWF, a named cohort, or the allocator itself is an African SWF/PF vehicle.
A43: Funds & LP Co-Investors | B43: 45 | C43: Injaro Ghana Venture Capital Fund (IGVCF) | D43: Specific names not individually disclosed | E43: Include | F43: Include | G43: Column H identifies a named African PF/SWF, a named cohort, or the allocator itself is an African SWF/PF vehicle.
A44: Funds & LP Co-Investors | B44: 46 | C44: NSSF Uganda Fund of Funds (planned) | D44: NSSF Uganda anchor (≥USD 15m + target other regional institutional investors) | E44: Exclude | F44: Excluded - insufficient actual African PF/SWF evidence | G44: Planned/prospective fund of funds, not a closed commitment as of audit date.
A45: Commitments Database | C45: SA infrastructure mandates via AOFSA | D45: KZN Municipal Pension Fund | E45: Exclude | F45: Excluded - mandate/member/planned evidence only | G45: Removed from commitments because the row evidenced membership, eligibility, MoU, expected follow-on, or planned allocation rather than an actual allocator-to-vehicle commitment.
A46: Commitments Database | C46: KEPFIC infrastructure + alts mandates | D46: KenGen Staff Retirement Benefits Scheme | E46: Exclude | F46: Excluded - mandate/member/planned evidence only | G46: Removed from commitments because the row evidenced membership, eligibility, MoU, expected follow-on, or planned allocation rather than an actual allocator-to-vehicle commitment.
A47: Commitments Database | C47: KEPFIC infrastructure + alts mandates | D47: Kenya Pipeline Company Staff Retirement Benefits Scheme | E47: Exclude | F47: Excluded - mandate/member/planned evidence only | G47: Removed from commitments because the row evidenced membership, eligibility, MoU, expected follow-on, or planned allocation rather than an actual allocator-to-vehicle commitment.
A48: Commitments Database | C48: KEPFIC infrastructure + alts mandates | D48: Kenya Revenue Authority (KRA) Staff Pension Scheme | E48: Exclude | F48: Excluded - mandate/member/planned evidence only | G48: Removed from commitments because the row evidenced membership, eligibility, MoU, expected follow-on, or planned allocation rather than an actual allocator-to-vehicle commitment.
A49: Commitments Database | C49: SA infrastructure mandates via AOFSA | D49: KwaZulu-Natal Joint Municipal Pension Fund (NJMPF) | E49: Exclude | F49: Excluded - mandate/member/planned evidence only | G49: Removed from commitments because the row evidenced membership, eligibility, MoU, expected follow-on, or planned allocation rather than an actual allocator-to-vehicle commitment.
A50: Commitments Database | C50: SA infrastructure mandates via AOFSA | D50: Motor Industry Retirement Fund (MIRF) | E50: Exclude | F50: Excluded - mandate/member/planned evidence only | G50: Removed from commitments because the row evidenced membership, eligibility, MoU, expected follow-on, or planned allocation rather than an actual allocator-to-vehicle commitment.
A51: Commitments Database | C51: ARM-Harith Climate and Transition Infrastructure Fund (ACT Fund) | D51: Multiple Nigerian PFAs (expected) | E51: Exclude | F51: Excluded - mandate/member/planned evidence only | G51: Removed from commitments because the row evidenced membership, eligibility, MoU, expected follow-on, or planned allocation rather than an actual allocator-to-vehicle commitment.
A52: Commitments Database | C52: Sahel Agribusiness Private Debt Fund | D52: Multiple Nigerian institutional investors (incl. PFAs) | E52: Exclude | F52: Excluded - mandate/member/planned evidence only | G52: Removed from commitments because the row evidenced membership, eligibility, MoU, expected follow-on, or planned allocation rather than an actual allocator-to-vehicle commitment.
A53: Commitments Database | C53: NSSF Uganda Fund of Funds (planned) | D53: NSSF Uganda | E53: Exclude | F53: Excluded - mandate/member/planned evidence only | G53: Removed from commitments because the row evidenced membership, eligibility, MoU, expected follow-on, or planned allocation rather than an actual allocator-to-vehicle commitment.
A54: Commitments Database | C54: SA infrastructure mandates via AOFSA | D54: National Fund for Municipal Workers (NFMW) | E54: Exclude | F54: Excluded - mandate/member/planned evidence only | G54: Removed from commitments because the row evidenced membership, eligibility, MoU, expected follow-on, or planned allocation rather than an actual allocator-to-vehicle commitment.
A55: Commitments Database | C55: KEPFIC infrastructure + alts mandates | D55: Safaricom Staff Pension Scheme | E55: Exclude | F55: Excluded - mandate/member/planned evidence only | G55: Removed from commitments because the row evidenced membership, eligibility, MoU, expected follow-on, or planned allocation rather than an actual allocator-to-vehicle commitment.
A56: Commitments Database | C56: Climate / infra mandate | D56: The Sovereign Fund of Egypt (TSFE) | E56: Exclude | F56: Excluded - mandate/member/planned evidence only | G56: Removed from commitments because the row evidenced membership, eligibility, MoU, expected follow-on, or planned allocation rather than an actual allocator-to-vehicle commitment.
A57: Funds & LP Co-Investors | C57: Africa Food Security Fund (AFSF) | D57: PIC on behalf of GEPF (South Africa) | E57: Include | F57: Include - confirmed African PF/SWF LP | G57: DGGF names PIC on behalf of GEPF as a first-round investor in AFSF alongside DFIs and DGGF; this is confirmed African pension fund involvement in a fund vehicle. | H57: https://english.dggf.nl/latest/news/2019/01/24/zebu-s-africa-food-security-fund-a-dggf-investee-reaches-total-fund-size-of-usd-84-million

Sheet Omission Candidates
A1: Candidate status | B1: Vehicle | C1: Manager / GP | D1: African PF/SWF evidence | E1: DFI / Other LP evidence | F1: Asset class | G1: Geographic focus | H1: Vintage / year | I1: Fund size / commitment evidence | J1: Confidence | K1: Recommended action | L1: Evidence summary | M1: Primary source URL | N1: Secondary source URL | O1: Search batch | P1: Date added
A2: Actioned - added to database | B2: Africa Food Security Fund (AFSF) | C2: Zebu Investment Partners | D2: PIC on behalf of GEPF (South Africa) | E2: AfDB; CDC Group/BII; Dutch Good Growth Fund; IFU; EBID; Kuramo Capital Management | F2: PE / agriculture / food security | G2: Sub-Saharan Africa | H2: 2019 | I2: DGGF says AFSF reached USD 84m; BII page says total commitments USD 90m | J2: H | K2: Already added to Commitments, Fund Vehicles, Source Library, Inclusion Audit, and DFI/Other LP patterns. | L2: DGGF names PIC on behalf of GEPF in first-round investors alongside DFIs and DGGF; BII confirms CDC invested alongside PIC and DFI group. | M2: https://english.dggf.nl/latest/news/2019/01/24/zebu-s-africa-food-security-fund-a-dggf-investee-reaches-total-fund-size-of-usd-84-million | N2: https://www.bii.co.uk/en/our-impact/fund/africa-food-security-fund-i-investment-01/ | O2: PIC/GEPF + DFI sweep | P2: 2026-05-19
A3: Candidate - likely add after row construction | B3: Pan African Infrastructure Development Fund (PAIDF) | C3: PAIDF Management Company / Harith-linked platform | D3: PIC/GEPF; Eskom Pension and Provident Fund; SSNIT Ghana; Metropolitan/Old Mutual/Stanlib named in source context | E3: AfDB; DBSA; Absa Capital; Barclays/ABSA Group | F3: Infrastructure | G3: Pan-Africa | H3: 2007 | I3: AfDB says target up to USD 450m initially; DBSA annual report says first close in Sep 2007 at USD 625m and DBSA committed USD 100m. | J3: H | K3: Add to Commitments and Fund Vehicles if historical scope includes older infrastructure funds; likely multiple African PF/SWF LP rows or a single aggregate historical PAIDF row. | L3: AfDB page names PIC/GEPF and EPPF as potential/reputable investors and PIC as chief sponsor; DBSA annual report says DBSA invested alongside PIC, AfDB, and SSNIT. | M3: https://www.afdb.org/en/news-and-events/pan-african-infrastructure-development-fund-paidf-afdb-group-proposes-us-50-million-investment-in-paidf-3476 | N3: https://www.dbsa.org/sites/default/files/media/documents/2021-09/DBSA%20and%20Development%20Fund%20Annual%20Reports%202008.pdf | O3: PIC/GEPF + DFI sweep | P3: 2026-05-19
A4: Candidate - new 2026 item | B4: Hlayisani Venture Fund II (HVF II) | C4: Hlayisani Capital | D4: Public Investment Corporation (PIC) | E4: SA SME Fund; additional private investors and family offices | F4: VC / technology-enabled SMEs | G4: South Africa | H4: 2026 | I4: R500m / about USD 30m commitments to date; final close targeted June 2026. | J4: H | K4: Add to Commitments and Fund Vehicles as confirmed first-close/commitments-to-date, with note that final close is pending. | L4: Hlayisani and multiple trade sources say Fund II is anchored by PIC and SA SME Fund with R500m committed to date. | M4: https://hlayisani.com/ | N4: https://disruptafrica.com/2026/03/11/sas-hlayisani-capital-launches-2nd-fund-with-initial-29-9m-in-commitments/ | O4: PIC/GEPF + recent fund-close sweep | P4: 2026-05-19
A5: Candidate - research vehicle identity | B5: Medu Capital Fund II | C5: Medu Capital | D5: Eskom Pension and Provident Fund; Public Investment Corporation | E5: DBSA; CDC Group; FMO; Alternative Equity Partners; Brait; Metropolitan; Vunani | F5: PE / BEE mid-market | G5: South Africa | H5: 2008 | I5: DBSA annual report says capitalisation R850m; DBSA provided R100m. | J5: M-H | K5: Review whether the vehicle is in scope as alternatives/fund LP; likely add if historical South Africa domestic PE vehicles are included. | L5: DBSA annual report identifies Medu II investors including EPPF, PIC, CDC, FMO and DBSA. | M5: https://www.dbsa.org/sites/default/files/media/documents/2021-09/DBSA%20and%20Development%20Fund%20Annual%20Reports%202008.pdf | O5: DBSA historical PE fund sweep | P5: 2026-05-19

Sheet Source Library
A1: Allocator | B1: Source type | C1: Title / publication | D1: Date accessed | E1: URL | F1: Used for
A2: PIC | B2: Press release | C2: Africa50: PIC becomes 36th shareholder | D2: May 2026 | E2: https://www.africa50.com/media/news/article/south-africas-public-investment-corporation-pic-becomes-36th-shareholder-of-africa50-with-a-us40-million-investment/ | F2: PIC USD 40m Africa50 investment April 2025
A3: PIC | B3: Corporate plan | C3: PIC Corporate Plan 2025/26 – 2027/28 | D3: May 2026 | E3: https://static.pmg.org.za/PIC_Corporate_Plan_2025.pdf | F3: PIC mandate restructuring; alts allocation programme
A4: PIC | B4: Trade press | C4: Africa's Largest Investment Manager Plans Big Shift to Private Assets (MarketsGroup) | D4: May 2026 | E4: https://www.marketsgroup.org/news/pic-plans-big-private-assets-shift | F4: PIC strategy shift toward private assets; prior R70bn PE allocation
A5: NSIA | B5: Press release | C5: NSIA to invest in Africa50 Infrastructure Acceleration Fund | D5: May 2026 | E5: https://nsia.com.ng/nigeria-sovereign-investment-authority-to-invest-in-africa50-infrastructure-acceleration-fund/ | F5: NSIA latest fund LP investment Feb 2026
A6: NSIA | B6: Profile | C6: NSIA Fund Profile – Global SWF | D6: May 2026 | E6: https://globalswf.com/fund/NSIA | F6: NSIA AUM and sub-fund structure
A7: NSIA | B7: DFI document | C7: AfDB Nigeria Sovereign Investment Authority Project Summary Note | D7: May 2026 | E7: https://www.afdb.org/en/documents/nigeria-nigeria-sovereign-investment-authority-project-summary-note | F7: AfDB co-financing with NSIA
A8: GIPF | B8: Allocator disclosure | C8: GIPF Unlisted Investments – Portfolio Overview | D8: May 2026 | E8: https://www.gipf.com.na/unlisted-investments/ | F8: GIPF alts portfolio detail (41 managers, 77 funds, 307 companies)
A9: GIPF | B9: Trade press | C9: Get a share of GIPF's Unlisted Investment Portfolio (New Era Live) | D9: May 2026 | E9: https://neweralive.na/get-a-share-of-gipfs-unlisted-investment-portfolio/ | F9: GIPF alts portfolio size and structure
A10: GIPF | B10: Allocator filing | C10: GIPF Investment Strategy and Policies | D10: May 2026 | E10: https://www.gipf.com.na/investment-policies/ | F10: Unlisted Investment Policy detail
A11: Helios | B11: Trade press | C11: Africa-Focused Helios Secures Lineup of Investors for CLEAR Fund's $200M First Close | D11: May 2026 | E11: https://globalaginvesting.com/africa-focused-helios-secures-lineup-of-investors-for-clear-funds-200m-first-close/ | F11: Helios CLEAR Fund first close; African pension LPs cited generically
A12: Helios | B12: Allocator disclosure | C12: Helios Investment Partners – Investments page | D12: May 2026 | E12: https://www.heliosinvestment.com/investments | F12: Helios portfolio and LP composition
... A179: GEPF / PIC | B179: DFI / fund announcement | C179: DGGF - Zebu Africa Food Security Fund reaches total fund size of USD 84 million | D179: May 2026 | E179: https://english.dggf.nl/latest/news/2019/01/24/zebu-s-africa-food-security-fund-a-dggf-investee-reaches-total-fund-size-of-usd-84-million | F179: PIC/GEPF LP confirmation in Africa Food Security Fund; co-investors AfDB, CDC/BII, DGGF, IFU, EBID and Kuramo

Sheet Absentees Investigation
A1: Tier 1 allocators with no disclosed African-alts commitments at fund or deal level — investigation into whether absence reflects regulatory constraint or under-disclosure.
A3: Institution | B3: Country | C3: AUM (USD m) | D3: Asset mix (most recent disclosed) | E3: Why absent: regulation vs behaviour | F3: Direction of travel | G3: Source
A4: NSSF Kenya | B4: Kenya | C4: 3200 | D4: 67.8% government securities; 14.5% quoted equities; 10.0% immovable property; 2.8% fixed deposits; 1.6% private equity & unlisted securities (KES 5.5bn) — up 597.8% YoY from 0.3% in 2023. Total alts (property + PE + REITs) ≈ 17.5% vs regulatory ceiling of ~70%. | E4: BEHAVIOUR (with major directional shift). RBA permits up to 10% in PE/VC. NSSF has historically deployed essentially zero in PE; the FY2024 disclosure of a 6-fold jump in unlisted exposure plus a stated MD intention to prioritise PE indicates this is becoming an emerging-allocation story, not a regulatory-block story. | F4: Active expansion underway | G4: Cytonn Retirement Benefits Schemes 2024 Performance Note; RBA Industry Brief Dec 2024; NSSF MD David Koros statements 2025–26
A5: POESSA Ethiopia | B5: Ethiopia | C5: 1500 | D5: Historical: ~100% government securities (Treasury bills, bonds) by legal mandate. Portfolio of ETB 183bn (~USD 1.5bn). Recent: amendment lifted T-bill / bond restriction; experimental real-estate allocation underway. | E5: REGULATION (until 2022) → RECENT LIBERALISATION. Until the 2022 amendment of POESSA's establishing proclamation, the agency was statutorily forbidden from investing outside T-bills and government bonds. The amendment now permits real-estate and broader securities; no disclosed PE/VC commitments yet. | F5: Newly permitted to allocate; ramping up | G5: The Reporter Ethiopia – Pension Fund Eyes Securities Exchange in Bid to Exercise New Investment Clause; ILO actuarial valuation workshop materials
A6: PSSSA / POESSA collectively (Ethiopia) | B6: Ethiopia | C6: 5000 | D6: Predominantly government securities and bank deposits; selected SOE stakes via Ethiopian Investment Holdings consolidation. | E6: REGULATION + STRUCTURAL. Ethiopian capital markets only opened with launch of Ethiopian Securities Exchange (planned). Limited domestic alts opportunity set; foreign-currency convertibility constraints limit pan-African commitments. | F6: Watch ESE launch + FX reform timeline | G6: ILO Ethiopia social-protection mapping; PSSSA / POESSA workshop materials
A7: PSSSF Tanzania | B7: Tanzania | C7: 6000 | D7: DSE-listed equities; government bonds; selected SOE/parastatal direct holdings; no disclosed alts commitments at fund level. Investment guidelines issued by Bank of Tanzania. | E7: REGULATION (effective). BoT investment guidelines are conservative; private equity is not an explicit permitted category in the same way as listed equities and bonds. PSSSF has Tanzania Agricultural Development Bank (TADB) as a partner but via direct credit rather than as an LP in a fund. | F7: No active liberalisation signal | G7: PSSSF investment guidelines (BoT); TADB partnership materials
A8: NSSF Tanzania | B8: Tanzania | C8: 1700 | D8: Government bonds, listed equities, real estate, fixed deposits. No disclosed PE/VC fund LP exposure. | E8: REGULATION (effective). Same BoT guideline regime as PSSSF. | F8: No active liberalisation signal | G8: PSSSF and NSSF Tanzania annual reports
A9: NOSI / NSSA Egypt | B9: Egypt | C9: 110000 | D9: Historically: ~99% in Egyptian government securities and bank deposits transferred to National Investment Bank (NIB). Statutory cap of 1% on capital-market investment. | E9: REGULATION (severe and active). Egyptian social insurance law obliged NOSI to transfer surpluses to NIB and capped capital-market investment at 1% of insurance funds. The 2019 Unified Social Insurance Law created a unified fund and moved management back to NOSI with a 'professional' investment board, but actual asset reallocation has been gradual. | F9: Recent governance reform; allocation reform pending | G9: World Bank Egypt pension reports; Loewe (2024) Social Security in Egypt analysis
A10: NIB Egypt (legacy pension assets) | B10: Egypt | C10: 30000 | D10: Treasury bills, public-sector deposits; minimal capital-market or alts exposure historically. | E10: REGULATION (effective). NIB exists in part as the legal recipient of NOSI surpluses; its mandate is government-financing, not alts allocation. | F10: Structure under reform | G10: World Bank Egypt pension reports
A11: Caisse Nationale de Retraites (Algeria) | B11: Algeria | C11: 3000 | D11: Predominantly Algerian government securities and bank deposits. | E11: REGULATION + MARKET. Algerian capital market is shallow; pension allocation is steered into government financing. | F11: No active liberalisation signal | G11: Algerian Ministry of Labour disclosures (limited)
A12: Libya Social Security Fund / LIA combined | B12: Libya | C12: 76000 | D12: LIA: bulk frozen under sanctions since 2011 (pre-2011 holdings included direct African bank, telecom stakes). SSF: domestic deposits and real estate. | E12: POLITICAL CONSTRAINT (sanctions on LIA); REGULATION + MARKET (SSF). | F12: Conflict-affected; reallocation contingent on political resolution | G12: UN Sanctions Committee disclosures; LIA reports (limited)
A13: Sonangol Pension Fund Angola | B13: Angola | C13: 800 | D13: Historically dominated by Angolan government securities and Sonangol-affiliated holdings; alts disclosure very limited. | E13: DISCLOSURE GAP (uncertain). Material AUM but minimal public reporting; unclear whether absence of disclosed alts commitments reflects regulation, behaviour, or simply opacity. | F13: Warrants follow-up via Angolan insurance regulator (ARSEG) | G13: ARSEG materials (limited); Sonangol corporate disclosures

Sheet Regulatory vs Behaviour
A1: Regulatory ceiling on alternative-asset allocation vs. actual disclosed allocation, top allocator institutions. Gap = headroom unused.
A3: Institution | B3: Country | C3: Regulator + key regulation | D3: Permitted PE / alts ceiling (%) | E3: Actual alts allocation (%, most recent) | F3: Headroom unused (% points) | G3: Story | H3: Source
A4: GEPF (managed by PIC) | B4: South Africa | C4: FSCA – Regulation 28 (effective Jan 2023) | D4: 15% private equity + 10% hedge funds (separate); 25% property | E4: ~20% across alternatives (PIC discloses ~20% alts overall) | F4: PE-equivalent ~5pp; SA equity 75% cap | G4: Headroom for further PE allocation exists post-2023 amendment; PIC has begun major shift toward private markets. | H4: Treasury Regulation 28 amendment 2022; PIC Corporate Plan 2025/26
A5: Other SA Reg-28 pension funds (EPPF, Transnet, Sentinel, umbrellas) | B5: South Africa | C5: FSCA – Regulation 28 | D5: 15% PE + 10% HF + 25% property | E5: EPPF ~10% alts (~4% PE); industry average lower | F5: PE ~11pp | G5: Industry-wide alts under-allocation relative to 2023 cap; SA pension industry consensus is alts allocation will rise. | H5: EPPF 2024 disclosures; SAVCA Pension Fund Study 2022; Glacier Insights
A6: Nigerian PFAs (CPS, all 19) | B6: Nigeria | C6: PenCom – Revised Investment Regulation Sept 2025 + addendum Feb 2026 | D6: PE: 10% (some funds) / 15% (others); infra funds also raised | E6: Aggregate ~5% in alts across the industry | F6: PE ~5–10pp | G6: Sept 2025 doubled PE cap; ARM-Harith ACT Fund (2025) designed with local-currency tranche to bypass FX barrier to further deployment. | H6: PenCom Revised Regulation 2025; PenCom Q1 2025 Report; Nairametrics 2026 addendum coverage
A7: NSSF Uganda | B7: Uganda | C7: URBRA Investment Guidelines | D7: 15% PE in EAC; 30% property; 5% other alts | E7: Long-term targets: 80% fixed income; 13.3% equities; 6.2% real estate. PE allocation small (Yield Uganda Investment Fund) | F7: PE ~13–14pp | G7: Stated long-term portfolio target sets only 6.2% real estate; URBRA allows up to 15% PE so significant unused headroom. Yield Uganda is the flagship PE programme but tiny relative to AUM. | H7: URBRA Investment Guidelines; NSSF Uganda 2024 Annual Integrated Report
A8: NSSF Kenya | B8: Kenya | C8: RBA – Retirement Benefits Regulations 2000 (as amended) | D8: 10% PE/VC; 70% total alts headroom across categories | E8: 1.6% PE/unlisted (June 2024, up from 0.3% in 2023); 17.5% total alts incl. property | F8: PE ~8.4pp | G8: Significant under-allocation but 597.8% YoY growth in PE bucket and explicit MD statement that PE is a 'top priority' for the next phase. | H8: Cytonn Retirement Schemes 2024; RBA Investment Guidelines; NSSF MD statements
A9: Other Kenyan schemes (occupational, umbrella) | B9: Kenya | C9: RBA | D9: 10% PE/VC | E9: Mostly <1% PE; aggregate Kenyan industry ~0.5–1% PE | F9: PE ~9pp | G9: Industry-wide under-utilisation of PE cap; few schemes have made commitments. | H9: RBA Industry Reports; Cytonn
A10: SSNIT Ghana | B10: Ghana | C10: NPRA – Guidelines on Investment of Pension Scheme Funds | D10: 10% per AI sub-asset class; 5% to open/closed-end funds | E10: 34% in 'alternatives' (real estate + PE + direct) as of 2023; rebalancing toward fixed income in 2024 | F10: Currently over the per-sub-class cap due to legacy concentration; reducing | G10: Counterexample case: Ghanaian SSNIT exceeded prudential targets through legacy property/direct holdings and is now reducing alts toward target, opposite direction to most peers. | H10: SSNIT 2022 Annual Report; B&FT 2024 reporting on SSNIT strategy shift
A11: Ghana Tier 2/3 schemes (corporate trustees) | B11: Ghana | C11: NPRA | D11: 10% per AI sub-asset class | E11: Aggregate ~5–8% in alts | F11: ~2–5pp | G11: Slowly increasing alts allocation; constrained by domestic alts pipeline. | H11: NPRA Investment Guidelines; news reports
A12: BPOPF Botswana | B12: Botswana | C12: NBFIRA – PFR2 (Pension Fund Investment Rules) | D12: 15% VC/PE (10% main + 5% offshore/local split); 50% min. domestic by Dec 2027 | E12: ~10% alts target / ~7–8% actual deployment | F12: PE ~5–7pp | G12: Active alts programme via incubation funds (Aleyo, Africa Lighthouse) plus mandates with Vantage and others; on track to fully use cap. | H12: NBFIRA PFR2 2023; SAVCA-FSDA 2022 study; BPOPF 2024 disclosures
A13: Other Botswana pension funds | B13: Botswana | C13: NBFIRA – PFR2 | D13: 15% VC/PE | E13: Aggregate ~5–8% | F13: PE ~7–10pp | G13: Industry mostly below cap; BPOPF leads sectoral practice. | H13: World Bank Botswana Financial Markets Diagnostic 2025
A14: GIPF Namibia | B14: Namibia | C14: NAMFISA – Pension Funds Act Regulation 28/29 | D14: Regulation 28 requires 35% min. in Namibian assets, max 3.5% via unlisted SPV vehicles. GIPF target: 10% PE + 5% RE (per its Unlisted Investment Policy). | E14: ~15% in alts (N$24.9bn committed of ~N$165bn AUM); 41 named managers | F14: At or near target; possibly above Reg 28 SPV cap depending on interpretation | G14: Namibia uniquely *mandates* unlisted exposure; GIPF is the most alts-deployed African pension fund. Regulatory interpretation of the 3.5% SPV cap vs direct unlisted is worth verifying for academic accuracy. | H14: GIPF Unlisted Investments disclosure; NAMFISA Reg 28/29; Old Mutual Namibia 2023 commentary
... A22: Ghana Tier 2/3 schemes — UPDATED (post-2026 5% rule) | B22: Ghana | C22: NPRA – Investment Guidelines (with 2026 'minimum 5% in alternative assets' policy) | D22: Minimum 5% in alts (newly mandated) | E22: Trustees beginning to deploy: Axis → GIP (USD 5m, Apr 2026); Axis + Enterprise → Ci Gaba FoF first close (Mar 2026, ~USD 35m total; Ghanaian pensions >2/3) | F22: Building toward 5% minimum | G22: Ghana has moved from permissive-only to MANDATED-MINIMUM alts allocation. Early commitments via Ci Gaba FoF (West Africa's first domestic-domiciled FoF) and GIP (BII platform with local-currency tranche) demonstrate that the policy is producing real flows. This is the most policy-design-relevant African case after Namibia's mandated-unlisted regime. | H22: BII GIP announcement April 2026; WeeTracker Ci Gaba coverage March 2026; Ecofin Agency

Sheet AVCA Aggregate vs Disclosed
A1: AVCA aggregate African-LP capital flow into African private capital vs. allocator-fund pairs disclosed in this database.
A3: Aggregate African-investor commitments to African private capital (per AVCA APCA Reports)
A5: Year | B5: Total African PE/VC/Infra fundraising (USD m) | C5: DFI contribution (USD m) | D5: DFI share (%) | E5: African investor contribution (USD m) | F5: African investor share (%)
A6: 2022 | B6: 1200 | C6: 708 | D6: 0.59 | E6: 171 | F6: 0.14
A7: 2023 | B7: Not separately disclosed | C7: — | D7: — | E7: — | F7: —
A8: 2024 | B8: 4000 | C8: 1400 | D8: 0.42 | E8: 639 | F8: 0.19
A11: The disclosure gap, quantified
A12: Metric | B12: 2024 figure | C12: Notes
A13: AVCA aggregate African-investor capital into African PE/VC/Infra (2024 only) | B13: USD 639m | C13: African pension funds + insurers + corporates combined
A14: Of which: catalogued in this database as 2024-vintage allocator-fund pairs (REVISED Phase 4-6) | B14: ~USD 200m (range USD 150–280m) | C14: Substantially revised upward from Phase 3 estimate (USD 100–150m) following Phases 4-6 DFI-platform-anchored search. See breakdown below.
A15: Implied 'untraceable' share of 2024 African-LP capital (REVISED) | B15: ~55–70% (was ~75–85% in Phase 3 estimate) | C15: Phase 4-6 closed a meaningful share of the gap by identifying the Africa50-IAF and Adenia V LP rosters. The residual gap is structural — pan-African flagship PE funds (ADP IV, Catalyst II, Vantage IV, Helios CLEAR) still report African pension LPs only categorically.
A16: Cumulative AVCA-tracked African-LP growth 2022 → 2024 | B16: 3.7x (USD 171m → USD 639m) | C16: Local capital share of total African PE/VC fundraising rose from 14% to 19%
A18: Breakdown of 2024-vintage traceable commitments (PE/VC/Infra fund LP only)
A19: Africa50 Infrastructure Acceleration Fund (IAF) — 2024 first close | B19: USD 222.5m total; ~USD 80–150m African PF/SWF share | C19: Named African LPs: NSIA Nigeria, CDC Sénégal, CDC Benin, CNSS Togo, CDG Invest Morocco. Press release said 'primarily from African institutional investors'.
A20: Adenia Capital V — April 2024 hard cap close ($470m) | B20: ~USD 30-80m African PF share | C20: Named LP: PIC SA (size not disclosed). Categorical 'Kenyan pension funds' and 'Ghanaian pension funds' cohorts (individual schemes not named).
A21: FONSIS → Oyass Capital — January 2024 | B21: ~USD 20–40m FONSIS share (of XOF 50bn / ~USD 82m fund) | C21: FONSIS co-anchor alongside KfW; SEAF as manager.
A22: Smaller 2024-vintage continental equity additions | B22: ~USD 10–30m | C22: Government of Egypt AFC equity (2024); incremental AFC equity allocations from existing shareholders.
A23: Sahel Agribusiness Private Debt Fund — 2024 launched | B23: Eligibility open; specific PFA commitments not yet disclosed | C23: NGN 75bn / ~USD 55.4m target; Stanbic IBTC in partner consortium.
A24: TOTAL traceable 2024-vintage African PF/SWF commitments | B24: ~USD 130–280m (mid ~USD 200m) | C24: Of AVCA-aggregate USD 639m for 2024 African-investor PE/VC/Infra capital.
A26: Cumulative across ALL vintages (not just 2024)
A27: Total named allocator-fund pairs catalogued in this database | B27: 86 commitments | C27: Across all vintages 2014-2026; ~30 unique African PF/SWF allocators.
A28: vs. Phase 2 baseline (initial allocator-side search) | B28: 27 commitments | C28: Phase 2 evidence harvest was anchored on allocator-side and marquee-GP-side search.
A29: Improvement factor | B29: ~3.2x | C29: DFI-platform-anchored search (Phases 4-6) tripled the named-LP coverage. The remaining gap is concentrated in pan-African flagship PE fund LP rosters where pension LPs appear only as categorical cohorts.
A32: Interpretation
A33: The AVCA aggregate confirms that African institutional capital flowing into local private capital has more than tripled in two years, and now constitutes 19% of all African private-capital fundraising. Following Phases 4-6 of this research (DFI-platform-anchored search), approximately 30-40% of the 2024 African-LP aggregate (USD 130-280m of USD 639m) is traceable to specific allocator-fund pairs in publicly available sources. This is materially better than the Phase 3 estimate of 15-25%, but the residual gap of 60-70% is structural. The remaining untraceable capital appears in two places: (a) pan-African flagship PE funds (Adenia V, ADP IV, Helios CLEAR, Phatisa FF3, Vantage IV) where African pension LPs are reported only as categorical cohorts; (b) commitments flowing through asset managers and umbrella vehicles where the ultimate asset owner is not separately disclosed. For academic publication this disclosure asymmetry is itself the principal methodological note — and the question of what disclosure regime would close it remains the principal policy contribution.
